{"referenceuuid":"59CF8851-1165-49EF-B982-5A4F2BB6F0CB","label":"Bezzi, M.  1918. Notes on the Ethiopian fruit-flies of the family Trypaneidae, other than Dacus (s.l.), with descriptions of new genera and species (Dipt.).-I. Bulletin of Entomological Research 8(3\/4): 215-251.","value":"Bezzi, M.  1918. Notes on the Ethiopian fruit-flies of the family Trypaneidae, other than Dacus (s.l.), with descriptions of new genera and species (Dipt.).-I. Bulletin of Entomological Research 8(3\/4): 215-251.","authorlist":"Bezzi, M.","year":"1918","title":"Notes on the Ethiopian fruit-flies of the family Trypaneidae, other than <em>Dacus<\/em> (s.l.), with descriptions of new genera and species (Dipt.).-I","citationdetails":"<em>Bulletin of Entomological Research<\/em> <b>8<\/b>(3\/4): 215-251.","volume":"8","number":"3\/4","edition":"","publisher":"","placepublished":"","pagination":"215-251","startpage":"215","endpage":"251","language":"English","languageid":"19691433","referencetype":"Journal Article","lsid":"urn:lsid:zoobank.org:pub:59CF8851-1165-49EF-B982-5A4F2BB6F0CB","parentreferenceid":"582D67DB-2B1E-4460-81C4-F671B8B51A5C","parentreference":"Bulletin of entomological research,  (Bull. Ent. Res.)","authors":[[{"familyname":"Bezzi","givenname":"M.","gnubuuid":"DBB0E441-18F7-4722-9815-369A3802F370"}]],"NomenclaturalActs":[{"tnuuuid":"E2305D6A-FA42-435F-AE86-F43B94038A8E","OriginalReferenceUUID":"59CF8851-1165-49EF-B982-5A4F2BB6F0CB","protonymuuid":"E2305D6A-FA42-435F-AE86-F43B94038A8E","label":"Baryglossa 1918","value":"Baryglossa 1918","lsid":"urn:lsid:zoobank.org:act:E2305D6A-FA42-435F-AE86-F43B94038A8E","parentname":"","namestring":"Baryglossa","rankgroup":"Genus","usageauthors":"","taxonnamerankid":"60","parentusageuuid":"","cleanprotonym":"Baryglossa Bezzi, 1918","NomenclaturalCode":"ICZN"},{"tnuuuid":"33D06305-2547-421A-A419-3979954CEB84","OriginalReferenceUUID":"3DCDB6B9-3711-4045-989C-BD81ADA8AFD9","protonymuuid":"6B84E9CB-0337-44B9-B52F-606603977D0E","label":"Euaresta 1873","value":"Euaresta 1873","lsid":"urn:lsid:zoobank.org:act:6B84E9CB-0337-44B9-B52F-606603977D0E","parentname":"","namestring":"Euaresta","rankgroup":"Genus","usageauthors":"Bezzi","taxonnamerankid":"60","parentusageuuid":"","cleanprotonym":"Euaresta Loew, 1873","NomenclaturalCode":"ICZN"},{"tnuuuid":"4EF28B5F-D8BF-4B6F-87F3-81AE1B7D75F9","OriginalReferenceUUID":"59CF8851-1165-49EF-B982-5A4F2BB6F0CB","protonymuuid":"4EF28B5F-D8BF-4B6F-87F3-81AE1B7D75F9","label":"Leucotaeniella 1918","value":"Leucotaeniella 1918","lsid":"urn:lsid:zoobank.org:act:4EF28B5F-D8BF-4B6F-87F3-81AE1B7D75F9","parentname":"","namestring":"Leucotaeniella","rankgroup":"Genus","usageauthors":"","taxonnamerankid":"60","parentusageuuid":"","cleanprotonym":"Leucotaeniella Bezzi, 1918","NomenclaturalCode":"ICZN"},{"tnuuuid":"67E557DB-3989-4B10-8516-6954CF09338B","OriginalReferenceUUID":"59CF8851-1165-49EF-B982-5A4F2BB6F0CB","protonymuuid":"67E557DB-3989-4B10-8516-6954CF09338B","label":"Pardalaspis 1918","value":"Pardalaspis 1918","lsid":"urn:lsid:zoobank.org:act:67E557DB-3989-4B10-8516-6954CF09338B","parentname":"","namestring":"Pardalaspis","rankgroup":"Genus","usageauthors":"","taxonnamerankid":"60","parentusageuuid":"","cleanprotonym":"Pardalaspis Bezzi, 1918","NomenclaturalCode":"ICZN"},{"tnuuuid":"A770D500-363E-4BB5-9059-BA13333AE2A6","OriginalReferenceUUID":"59CF8851-1165-49EF-B982-5A4F2BB6F0CB","protonymuuid":"A770D500-363E-4BB5-9059-BA13333AE2A6","label":"Pterandrus 1918","value":"Pterandrus 1918","lsid":"urn:lsid:zoobank.org:act:A770D500-363E-4BB5-9059-BA13333AE2A6","parentname":"","namestring":"Pterandrus","rankgroup":"Genus","usageauthors":"","taxonnamerankid":"60","parentusageuuid":"","cleanprotonym":"Pterandrus Bezzi, 1918","NomenclaturalCode":"ICZN"},{"tnuuuid":"75806CB0-6FAD-4C83-8384-2D63A8BA30AF","OriginalReferenceUUID":"59CF8851-1165-49EF-B982-5A4F2BB6F0CB","protonymuuid":"75806CB0-6FAD-4C83-8384-2D63A8BA30AF","label":"Trirhithrum 1918","value":"Trirhithrum 1918","lsid":"urn:lsid:zoobank.org:act:75806CB0-6FAD-4C83-8384-2D63A8BA30AF","parentname":"","namestring":"Trirhithrum","rankgroup":"Genus","usageauthors":"","taxonnamerankid":"60","parentusageuuid":"","cleanprotonym":"Trirhithrum Bezzi, 1918","NomenclaturalCode":"ICZN"},{"tnuuuid":"6DE05C52-B4DA-40F6-AAD5-2316FAADA8E1","OriginalReferenceUUID":"59CF8851-1165-49EF-B982-5A4F2BB6F0CB","protonymuuid":"6DE05C52-B4DA-40F6-AAD5-2316FAADA8E1","label":"Pliomelaena 1918","value":"Pliomelaena 1918","lsid":"urn:lsid:zoobank.org:act:6DE05C52-B4DA-40F6-AAD5-2316FAADA8E1","parentname":"","namestring":"Pliomelaena","rankgroup":"Genus","usageauthors":"","taxonnamerankid":"63","parentusageuuid":"33D06305-2547-421A-A419-3979954CEB84","cleanprotonym":"Euaresta (Pliomelaena) Bezzi, 1918","NomenclaturalCode":"ICZN"},{"tnuuuid":"71FC65E4-405B-4478-B1F5-1423439764ED","OriginalReferenceUUID":"59CF8851-1165-49EF-B982-5A4F2BB6F0CB","protonymuuid":"71FC65E4-405B-4478-B1F5-1423439764ED","label":"histrio 1918","value":"histrio 1918","lsid":"urn:lsid:zoobank.org:act:71FC65E4-405B-4478-B1F5-1423439764ED","parentname":"Baryglossa","namestring":"histrio","rankgroup":"Species","usageauthors":"","taxonnamerankid":"70","parentusageuuid":"E2305D6A-FA42-435F-AE86-F43B94038A8E","cleanprotonym":"Baryglossa histrio Bezzi, 1918","NomenclaturalCode":"ICZN"},{"tnuuuid":"6A2CA30E-B9E6-430F-AEE9-4136C48AC1BD","OriginalReferenceUUID":"59CF8851-1165-49EF-B982-5A4F2BB6F0CB","protonymuuid":"6A2CA30E-B9E6-430F-AEE9-4136C48AC1BD","label":"trispila 1918","value":"trispila 1918","lsid":"urn:lsid:zoobank.org:act:6A2CA30E-B9E6-430F-AEE9-4136C48AC1BD","parentname":"Leucotaeniella","namestring":"trispila","rankgroup":"Species","usageauthors":"","taxonnamerankid":"70","parentusageuuid":"4EF28B5F-D8BF-4B6F-87F3-81AE1B7D75F9","cleanprotonym":"Leucotaeniella trispila Bezzi, 1918","NomenclaturalCode":"ICZN"}],"doi":"10.1017\/s0007485300037640"}