{"referenceuuid":"90F6E6B8-A903-44DB-AD0E-3D851F6454C9","label":"Papp, Jeno.  2012. Five new braconid species from Colombia (Hymenoptera, Braconidae). Journal of Hymenoptera Research 28: 67-84.","value":"Papp, Jeno.  2012. Five new braconid species from Colombia (Hymenoptera, Braconidae). Journal of Hymenoptera Research 28: 67-84.","authorlist":"Papp, Jeno.","year":"2012","title":"Five new braconid species from Colombia (Hymenoptera, Braconidae)","citationdetails":"<em>Journal of Hymenoptera Research<\/em> <b>28<\/b>: 67-84.","volume":"28","number":"","edition":"","publisher":"","placepublished":"","pagination":"67-84, 57","startpage":"67","endpage":"84","language":"English","languageid":"19691433","referencetype":"Journal Article","lsid":"urn:lsid:zoobank.org:pub:90F6E6B8-A903-44DB-AD0E-3D851F6454C9","parentreferenceid":"55528528-5C97-4D79-A718-8B3D153B37CC","parentreference":"Journal of Hymenoptera Research,  (J. Hymenoptera Res.)","authors":[[{"familyname":"Papp","givenname":"Jeno","gnubuuid":"445C9BCE-4785-4489-8501-33B7A7CF3B60"}]],"NomenclaturalActs":[{"tnuuuid":"B46F9BF7-F36F-4F9E-9B41-4B9B872540A6","OriginalReferenceUUID":"53DDFBC2-F91D-4C99-AD84-56C3DDBF17F7","protonymuuid":"79AEF102-223F-4E7D-9E86-25D4C8A7AFF7","label":"Aspilota 1862","value":"Aspilota 1862","lsid":"urn:lsid:zoobank.org:act:79AEF102-223F-4E7D-9E86-25D4C8A7AFF7","parentname":"","namestring":"Aspilota","rankgroup":"Genus","usageauthors":"Papp","taxonnamerankid":"60","parentusageuuid":"","cleanprotonym":"Aspilota F\u00f6rster, 1862","NomenclaturalCode":"ICZN"},{"tnuuuid":"621B1BCD-9A45-499A-AD6A-8EB2552B46EF","OriginalReferenceUUID":"1144DE65-7CE3-4FFF-B8E5-1F878A5AE482","protonymuuid":"65F2C58C-AC8E-4E5A-91EE-81B7DD12C404","label":"Blacus Nees von Esenbeck 1818","value":"Blacus Nees von Esenbeck 1818","lsid":"urn:lsid:zoobank.org:act:65F2C58C-AC8E-4E5A-91EE-81B7DD12C404","parentname":"","namestring":"Blacus","rankgroup":"Genus","usageauthors":"Papp","taxonnamerankid":"60","parentusageuuid":"","cleanprotonym":"Blacus Nees von Esenbeck, 1818","NomenclaturalCode":"ICZN"},{"tnuuuid":"18C12DC1-99C7-47AC-9B55-5E1839E439E1","OriginalReferenceUUID":"","protonymuuid":"3C39980C-4970-486B-ACFE-241C5F52E6CB","label":"Pseudorhysipolis  [placeholder record]","value":"Pseudorhysipolis  [placeholder record]","lsid":"","parentname":"","namestring":"Pseudorhysipolis","rankgroup":"Genus","usageauthors":"Papp","taxonnamerankid":"60","parentusageuuid":"","cleanprotonym":"Pseudorhysipolis","NomenclaturalCode":"ICZN"},{"tnuuuid":"F391E1D6-9C57-4593-9AE6-3144E2709268","OriginalReferenceUUID":"","protonymuuid":"835DB940-07F4-44F2-BD80-6AF97636E5EA","label":"Synaldis  [placeholder record]","value":"Synaldis  [placeholder record]","lsid":"","parentname":"","namestring":"Synaldis","rankgroup":"Genus","usageauthors":"Papp","taxonnamerankid":"60","parentusageuuid":"","cleanprotonym":"Synaldis","NomenclaturalCode":"ICZN"},{"tnuuuid":"6F9EFAFB-3F27-4A38-BFE9-C84E3B673E0A","OriginalReferenceUUID":"90F6E6B8-A903-44DB-AD0E-3D851F6454C9","protonymuuid":"6F9EFAFB-3F27-4A38-BFE9-C84E3B673E0A","label":"Telmogarbus Papp 2012","value":"Telmogarbus Papp 2012","lsid":"urn:lsid:zoobank.org:act:6F9EFAFB-3F27-4A38-BFE9-C84E3B673E0A","parentname":"","namestring":"Telmogarbus","rankgroup":"Genus","usageauthors":"Papp","taxonnamerankid":"60","parentusageuuid":"","cleanprotonym":"Telmogarbus Papp, 2012","NomenclaturalCode":"ICZN"},{"tnuuuid":"0F26E475-5F9E-4F96-8407-AC2DD4BED718","OriginalReferenceUUID":"90F6E6B8-A903-44DB-AD0E-3D851F6454C9","protonymuuid":"0F26E475-5F9E-4F96-8407-AC2DD4BED718","label":"stigmalis Papp 2012","value":"stigmalis Papp 2012","lsid":"urn:lsid:zoobank.org:act:0F26E475-5F9E-4F96-8407-AC2DD4BED718","parentname":"Aspilota","namestring":"stigmalis","rankgroup":"Species","usageauthors":"Papp","taxonnamerankid":"70","parentusageuuid":"B46F9BF7-F36F-4F9E-9B41-4B9B872540A6","cleanprotonym":"Aspilota stigmalis Papp, 2012","NomenclaturalCode":"ICZN"},{"tnuuuid":"AF970EB5-9078-4098-AE34-B6B8D1B0AD93","OriginalReferenceUUID":"90F6E6B8-A903-44DB-AD0E-3D851F6454C9","protonymuuid":"AF970EB5-9078-4098-AE34-B6B8D1B0AD93","label":"latestigma Papp 2012","value":"latestigma Papp 2012","lsid":"urn:lsid:zoobank.org:act:AF970EB5-9078-4098-AE34-B6B8D1B0AD93","parentname":"Blacus","namestring":"latestigma","rankgroup":"Species","usageauthors":"Papp","taxonnamerankid":"70","parentusageuuid":"621B1BCD-9A45-499A-AD6A-8EB2552B46EF","cleanprotonym":"Blacus latestigma Papp, 2012","NomenclaturalCode":"ICZN"},{"tnuuuid":"8076B0BB-A892-4EF2-B203-345925A26426","OriginalReferenceUUID":"90F6E6B8-A903-44DB-AD0E-3D851F6454C9","protonymuuid":"8076B0BB-A892-4EF2-B203-345925A26426","label":"inaequalis Papp 2012","value":"inaequalis Papp 2012","lsid":"urn:lsid:zoobank.org:act:8076B0BB-A892-4EF2-B203-345925A26426","parentname":"Pseudorhysipolis","namestring":"inaequalis","rankgroup":"Species","usageauthors":"Papp","taxonnamerankid":"70","parentusageuuid":"18C12DC1-99C7-47AC-9B55-5E1839E439E1","cleanprotonym":"Pseudorhysipolis inaequalis Papp, 2012","NomenclaturalCode":"ICZN"},{"tnuuuid":"78AEA130-5EF3-4FD2-A9BF-0415E0DCAFBC","OriginalReferenceUUID":"90F6E6B8-A903-44DB-AD0E-3D851F6454C9","protonymuuid":"78AEA130-5EF3-4FD2-A9BF-0415E0DCAFBC","label":"cauca Papp 2012","value":"cauca Papp 2012","lsid":"urn:lsid:zoobank.org:act:78AEA130-5EF3-4FD2-A9BF-0415E0DCAFBC","parentname":"Synaldis","namestring":"cauca","rankgroup":"Species","usageauthors":"Papp","taxonnamerankid":"70","parentusageuuid":"F391E1D6-9C57-4593-9AE6-3144E2709268","cleanprotonym":"Synaldis cauca Papp, 2012","NomenclaturalCode":"ICZN"},{"tnuuuid":"198BCB2B-3030-4C87-B2D3-D944CFA2E478","OriginalReferenceUUID":"90F6E6B8-A903-44DB-AD0E-3D851F6454C9","protonymuuid":"198BCB2B-3030-4C87-B2D3-D944CFA2E478","label":"olivai Papp 2012","value":"olivai Papp 2012","lsid":"urn:lsid:zoobank.org:act:198BCB2B-3030-4C87-B2D3-D944CFA2E478","parentname":"Telmogarbus Papp, 2012","namestring":"olivai","rankgroup":"Species","usageauthors":"Papp","taxonnamerankid":"70","parentusageuuid":"6F9EFAFB-3F27-4A38-BFE9-C84E3B673E0A","cleanprotonym":"Telmogarbus olivai Papp, 2012","NomenclaturalCode":"ICZN"}],"doi":"10.3897\/jhr.28.2023"}