{"referenceuuid":"CABA56B3-5F25-45F1-B355-3B28D0032012","label":"Wang, Zongqing & Yanli Che.  2013. Three new species of cockroach genus Symploce Hebard, 1916 (Blattodea, Ectobiidae, Blattellinae) with redescriptions of two known species based on types from Mainland China. ZooKeys 337: 1-18.","value":"Wang, Zongqing & Yanli Che.  2013. Three new species of cockroach genus Symploce Hebard, 1916 (Blattodea, Ectobiidae, Blattellinae) with redescriptions of two known species based on types from Mainland China. ZooKeys 337: 1-18.","authorlist":"Wang, Zongqing & Yanli Che.","year":"2013","title":"Three new species of cockroach genus <em>Symploce<\/em> Hebard, 1916 (Blattodea, Ectobiidae, Blattellinae) with redescriptions of two known species based on types from Mainland China","citationdetails":"<em>ZooKeys<\/em> <b>337<\/b>: 1-18.","volume":"337","number":"","edition":"","publisher":"","placepublished":"","pagination":"1-18","startpage":"1","endpage":"18","language":"English","languageid":"19691433","referencetype":"Journal Article","lsid":"urn:lsid:zoobank.org:pub:CABA56B3-5F25-45F1-B355-3B28D0032012","parentreferenceid":"91BD42D4-90F1-4B45-9350-EEF175B1727A","parentreference":"ZooKeys","authors":[[{"familyname":"Wang","givenname":"Zongqing","gnubuuid":"B29AEB84-9DB0-4C98-9CE8-FD5BC875771B"}],[{"familyname":"Che","givenname":"Yanli","gnubuuid":"8ED9AE03-E0EB-4DCE-BE08-658582983CC4"}]],"NomenclaturalActs":[{"tnuuuid":"B282C0BF-7BC4-4753-B0AD-6F9D5016876F","OriginalReferenceUUID":"","protonymuuid":"D27AEFCB-5B72-484B-8611-B08711864E1E","label":"Symploce  [placeholder record]","value":"Symploce  [placeholder record]","lsid":"","parentname":"","namestring":"Symploce","rankgroup":"Genus","usageauthors":"Wang & Che","taxonnamerankid":"60","parentusageuuid":"","cleanprotonym":"Symploce","NomenclaturalCode":"ICZN"},{"tnuuuid":"CFD981C4-9590-4294-BC9A-C73EDABF8DDF","OriginalReferenceUUID":"CABA56B3-5F25-45F1-B355-3B28D0032012","protonymuuid":"CFD981C4-9590-4294-BC9A-C73EDABF8DDF","label":"evidens 2013","value":"evidens 2013","lsid":"urn:lsid:zoobank.org:act:CFD981C4-9590-4294-BC9A-C73EDABF8DDF","parentname":"Symploce","namestring":"evidens","rankgroup":"Species","usageauthors":"","taxonnamerankid":"70","parentusageuuid":"B282C0BF-7BC4-4753-B0AD-6F9D5016876F","cleanprotonym":"Symploce evidens Wang & Che, 2013","NomenclaturalCode":"ICZN"},{"tnuuuid":"66C616E4-5D66-428F-9F29-6C94E374B0EF","OriginalReferenceUUID":"CABA56B3-5F25-45F1-B355-3B28D0032012","protonymuuid":"66C616E4-5D66-428F-9F29-6C94E374B0EF","label":"paramarginata 2013","value":"paramarginata 2013","lsid":"urn:lsid:zoobank.org:act:66C616E4-5D66-428F-9F29-6C94E374B0EF","parentname":"Symploce","namestring":"paramarginata","rankgroup":"Species","usageauthors":"","taxonnamerankid":"70","parentusageuuid":"B282C0BF-7BC4-4753-B0AD-6F9D5016876F","cleanprotonym":"Symploce paramarginata Wang & Che, 2013","NomenclaturalCode":"ICZN"},{"tnuuuid":"54B15C64-8C73-4A8B-A6AA-185AB2107546","OriginalReferenceUUID":"CABA56B3-5F25-45F1-B355-3B28D0032012","protonymuuid":"54B15C64-8C73-4A8B-A6AA-185AB2107546","label":"sphaerica 2013","value":"sphaerica 2013","lsid":"urn:lsid:zoobank.org:act:54B15C64-8C73-4A8B-A6AA-185AB2107546","parentname":"Symploce","namestring":"sphaerica","rankgroup":"Species","usageauthors":"","taxonnamerankid":"70","parentusageuuid":"B282C0BF-7BC4-4753-B0AD-6F9D5016876F","cleanprotonym":"Symploce sphaerica Wang & Che, 2013","NomenclaturalCode":"ICZN"}],"doi":"10.3897\/zookeys.337.5770"}