{"referenceuuid":"22D78A20-7E3D-4AC2-B252-33C58F0156EF","label":"Ahnelt, H. & P. G. Bianco.  1990. Orsinigobius milleri n. sp., a new species of freshwater goby from W-Greece (Pisces: Gobiidae). Annalen des Naturhistorischen Museums in Wien, Serie B, Botanik und Zoologie 91 B: 1-6.","value":"Ahnelt, H. & P. G. Bianco.  1990. Orsinigobius milleri n. sp., a new species of freshwater goby from W-Greece (Pisces: Gobiidae). Annalen des Naturhistorischen Museums in Wien, Serie B, Botanik und Zoologie 91 B: 1-6.","authorlist":"Ahnelt, H. & P. G. Bianco.","year":"1990","title":"<i>Orsinigobius milleri<\/i> n. sp., a new species of freshwater goby from W-Greece (Pisces: Gobiidae)","citationdetails":"<em>Annalen des Naturhistorischen Museums in Wien, Serie B, Botanik und Zoologie<\/em> <b>91 B<\/b>: 1-6.","volume":"91 B","number":"","edition":"","publisher":"","placepublished":"","pagination":"1-6","startpage":"1","endpage":"6","language":"","languageid":"0","referencetype":"Journal Article","lsid":"urn:lsid:zoobank.org:pub:22D78A20-7E3D-4AC2-B252-33C58F0156EF","parentreferenceid":"989C54B8-7C71-49AD-90D8-B04CA95AC28C","parentreference":"Annalen des Naturhistorischen Museums in Wien, Serie B, Botanik und Zoologie (Ann. Naturhist. Mus. Wien)","authors":[[{"familyname":"Ahnelt","givenname":"H.","gnubuuid":"228957B3-8DE3-4C1A-BBF3-92031F83BA84"}],[{"familyname":"Bianco","givenname":"P. G.","gnubuuid":"9D953672-479E-4ABB-8E95-796BC0536A92"}]],"NomenclaturalActs":[{"tnuuuid":"3F34CA02-0B5E-4D4F-9139-C9645DF8ABDF","OriginalReferenceUUID":"A5429256-6C5E-4163-BD64-A7A5F1448652","protonymuuid":"844E8E0F-20AF-407D-A5E4-5BDDC3F55CAD","label":"Orsinigobius Gandolfi, Marconato & Torricelli 1986","value":"Orsinigobius Gandolfi, Marconato & Torricelli 1986","lsid":"urn:lsid:zoobank.org:act:844E8E0F-20AF-407D-A5E4-5BDDC3F55CAD","parentname":"","namestring":"Orsinigobius","rankgroup":"Genus","usageauthors":"Ahnelt & Bianco","taxonnamerankid":"60","parentusageuuid":"","cleanprotonym":"Orsinigobius Gandolfi, Marconato & Torricelli, 1986","NomenclaturalCode":"ICZN"},{"tnuuuid":"F82B43C3-706A-45E5-8BDD-B4BE73DCA6D2","OriginalReferenceUUID":"22D78A20-7E3D-4AC2-B252-33C58F0156EF","protonymuuid":"F82B43C3-706A-45E5-8BDD-B4BE73DCA6D2","label":"milleri Ahnelt & Bianco 1990","value":"milleri Ahnelt & Bianco 1990","lsid":"urn:lsid:zoobank.org:act:F82B43C3-706A-45E5-8BDD-B4BE73DCA6D2","parentname":"Orsinigobius","namestring":"milleri","rankgroup":"Species","usageauthors":"Ahnelt & Bianco","taxonnamerankid":"70","parentusageuuid":"3F34CA02-0B5E-4D4F-9139-C9645DF8ABDF","cleanprotonym":"Orsinigobius milleri Ahnelt & Bianco, 1990","NomenclaturalCode":"ICZN"}]}