{"referenceuuid":"F26B4967-3703-46A4-A894-1B7904B0C6AA","label":"Vanin, Sergio A. & Bruno A. S. De Medeiros.  2013. A new species of Sicoderus Vanin from Bolivia (Coleoptera: Curculionidae: Curculioninae: Otidocephalini). Zootaxa 3734(1): 81-85.","value":"Vanin, Sergio A. & Bruno A. S. De Medeiros.  2013. A new species of Sicoderus Vanin from Bolivia (Coleoptera: Curculionidae: Curculioninae: Otidocephalini). Zootaxa 3734(1): 81-85.","authorlist":"Vanin, Sergio A. & Bruno A. S. De Medeiros.","year":"2013","title":"A new species of <em>Sicoderus <\/em>Vanin from Bolivia (Coleoptera: Curculionidae: Curculioninae: Otidocephalini)","citationdetails":"<em>Zootaxa<\/em> <b>3734<\/b>(1): 81-85.","volume":"3734","number":"1","edition":"","publisher":"","placepublished":"","pagination":"81-85","startpage":"81","endpage":"85","language":"English","languageid":"19691433","referencetype":"Journal Article","lsid":"urn:lsid:zoobank.org:pub:F26B4967-3703-46A4-A894-1B7904B0C6AA","parentreferenceid":"78F99150-21C2-4639-B359-F3E2302DF0B7","parentreference":"Zootaxa","authors":[[{"familyname":"Vanin","givenname":"Sergio Antonio","gnubuuid":"5EDCBA0E-37F4-4AA1-B8F0-9084AA9CB19F"}],[{"familyname":"Medeiros","givenname":"Bruno A. S. De","gnubuuid":"3723FFDB-6F23-4327-AC6B-969082DBB503"}]],"NomenclaturalActs":[{"tnuuuid":"072e2edf-dfd1-4e69-8a52-b7d9edf939bd","OriginalReferenceUUID":"","protonymuuid":"3a63901c-aad5-41b2-9a65-5a2d0ddf52c3","label":"Sicoderus Vanin 1986  [placeholder record]","value":"Sicoderus Vanin 1986  [placeholder record]","lsid":"urn:lsid:zoobank.org:act:3A63901C-AAD5-41B2-9A65-5A2D0DDF52C3","parentname":"","namestring":"Sicoderus","rankgroup":"Genus","usageauthors":"Vanin & Medeiros","taxonnamerankid":"60","parentusageuuid":"","cleanprotonym":"Sicoderus Vanin 1986","NomenclaturalCode":"ICZN"},{"tnuuuid":"9edc15ad-ebab-45cc-891a-9ff83bf55a36","OriginalReferenceUUID":"f26b4967-3703-46a4-a894-1b7904b0c6aa","protonymuuid":"9edc15ad-ebab-45cc-891a-9ff83bf55a36","label":"robini Vanin & Medeiros 2013","value":"robini Vanin & Medeiros 2013","lsid":"urn:lsid:zoobank.org:act:9EDC15AD-EBAB-45CC-891A-9FF83BF55A36","parentname":"","namestring":"robini","rankgroup":"Species","usageauthors":"Vanin & Medeiros","taxonnamerankid":"70","parentusageuuid":"072e2edf-dfd1-4e69-8a52-b7d9edf939bd","cleanprotonym":"Sicoderus robini Vanin & Medeiros, 2013","NomenclaturalCode":"ICZN"}],"doi":"10.11646\/zootaxa.3734.1.9"}