{ "referenceuuid":"5C976427-D013-4B0F-BABE-6BF94B4646C8","label": "Bellamy, Charles L. & Richard L. Westcott.  2003. Correction to the Buprestidae and Schizopodidae (Coleoptera) listings from Nomina Insecta Nearctica (1996). Zootaxa 147: 1-20.", "value": "Bellamy, Charles L. & Richard L. Westcott.  2003. Correction to the Buprestidae and Schizopodidae (Coleoptera) listings from Nomina Insecta Nearctica (1996). Zootaxa 147: 1-20.", "authorlist" : "Bellamy, Charles L. & Richard L. Westcott.", "year" : "2003", "title" : "Correction to the Buprestidae and Schizopodidae (Coleoptera) listings from <i>Nomina Insecta Nearctica<\/i> (1996).", "citationdetails" : "<em>Zootaxa<\/em> <b>147<\/b>: 1-20.","volume":"147","number":"","edition":"","publisher":"","placepublished":"","pagination":"1-20","startpage":"1","endpage":"20","language":"English","languageid":"19691433","referencetype":"Journal Article","lsid":"urn:lsid:zoobank.org:pub:5C976427-D013-4B0F-BABE-6BF94B4646C8","parentreferenceid":"78F99150-21C2-4639-B359-F3E2302DF0B7","parentreference":"Zootaxa","authors":[[{"familyname":"Bellamy","givenname":"Charles L.","gnubuuid":"0B1B382E-B179-4BAE-A8E7-2C9CF72DE570"}],[{"familyname":"Westcott","givenname":"Richard L.","gnubuuid":"114D4E0E-886D-4493-92D7-63D1DDB6B0C3"}]]}