{"referenceuuid":"5CDD59D4-8479-4C76-B689-DDC80C5B10B0","label":"Kustov, Semen & Igor Shamshev.  2014. A review of dance-flies of the Empis (s. str.) pennipes group of species (Diptera: Empididae) from the Caucasus, with descriptions of five new species. Caucasian Entomological Bulletin 10(1): 170-184.","value":"Kustov, Semen & Igor Shamshev.  2014. A review of dance-flies of the Empis (s. str.) pennipes group of species (Diptera: Empididae) from the Caucasus, with descriptions of five new species. Caucasian Entomological Bulletin 10(1): 170-184.","authorlist":"Kustov, Semen & Igor Shamshev.","year":"2014","title":"A review of dance-flies of the <em>Empis<\/em> (s. str.) <em>pennipes<\/em> group of species (Diptera: Empididae) from the Caucasus, with descriptions of five new species","citationdetails":"<em>Caucasian Entomological Bulletin<\/em> <b>10<\/b>(1): 170-184.","volume":"10","number":"1","edition":"","publisher":"","placepublished":"","pagination":"170-184","startpage":"170","endpage":"184","language":"Russian","languageid":"19691407","referencetype":"Journal Article","lsid":"urn:lsid:zoobank.org:pub:5CDD59D4-8479-4C76-B689-DDC80C5B10B0","parentreferenceid":"E764ECF0-4F3B-499D-82A5-00099C32E9E1","parentreference":"Caucasian Entomological Bulletin,  (Caucas. entomol. bull.)","authors":[[{"familyname":"Kustov","givenname":"Semen","gnubuuid":"E930672A-0A39-4C50-A610-A1C73D86406E"}],[{"familyname":"Shamshev","givenname":"Igor","gnubuuid":"407DA87B-4380-4FBC-9558-3765AD5255F7"}]],"NomenclaturalActs":[{"tnuuuid":"A0020B63-C2AA-4203-847A-70ACEED78C09","OriginalReferenceUUID":"2C6327E1-5560-4DB4-B9CA-76A0FA03D975","protonymuuid":"C20BD36B-9324-4E23-968D-E715857E747A","label":"Empis Linn\u00e6us 1758","value":"Empis Linn\u00e6us 1758","lsid":"urn:lsid:zoobank.org:act:C20BD36B-9324-4E23-968D-E715857E747A","parentname":"","namestring":"Empis","rankgroup":"Genus","usageauthors":"Kustov & Shamshev","taxonnamerankid":"60","parentusageuuid":"","cleanprotonym":"Empis Linn\u00e6us, 1758","NomenclaturalCode":"ICZN"},{"tnuuuid":"F124F387-7465-4B06-A93F-58322CFDAA98","OriginalReferenceUUID":"5CDD59D4-8479-4C76-B689-DDC80C5B10B0","protonymuuid":"F124F387-7465-4B06-A93F-58322CFDAA98","label":"batumiensis 2014","value":"batumiensis 2014","lsid":"urn:lsid:zoobank.org:act:F124F387-7465-4B06-A93F-58322CFDAA98","parentname":"Empis Linn\u00e6us, 1758","namestring":"batumiensis","rankgroup":"Species","usageauthors":"","taxonnamerankid":"70","parentusageuuid":"A0020B63-C2AA-4203-847A-70ACEED78C09","cleanprotonym":"Empis batumiensis Kustov & Shamshev, 2014","NomenclaturalCode":"ICZN"},{"tnuuuid":"B3AFDA17-1613-438C-9FFC-2FA9047BFCE5","OriginalReferenceUUID":"5CDD59D4-8479-4C76-B689-DDC80C5B10B0","protonymuuid":"B3AFDA17-1613-438C-9FFC-2FA9047BFCE5","label":"caucasimontanus 2014","value":"caucasimontanus 2014","lsid":"urn:lsid:zoobank.org:act:B3AFDA17-1613-438C-9FFC-2FA9047BFCE5","parentname":"Empis Linn\u00e6us, 1758","namestring":"caucasimontanus","rankgroup":"Species","usageauthors":"","taxonnamerankid":"70","parentusageuuid":"A0020B63-C2AA-4203-847A-70ACEED78C09","cleanprotonym":"Empis caucasimontanus Kustov & Shamshev, 2014","NomenclaturalCode":"ICZN"},{"tnuuuid":"F7A7BA6A-3673-49A7-A7E3-E794724867E9","OriginalReferenceUUID":"5CDD59D4-8479-4C76-B689-DDC80C5B10B0","protonymuuid":"F7A7BA6A-3673-49A7-A7E3-E794724867E9","label":"caucasipennipes 2014","value":"caucasipennipes 2014","lsid":"urn:lsid:zoobank.org:act:F7A7BA6A-3673-49A7-A7E3-E794724867E9","parentname":"Empis Linn\u00e6us, 1758","namestring":"caucasipennipes","rankgroup":"Species","usageauthors":"","taxonnamerankid":"70","parentusageuuid":"A0020B63-C2AA-4203-847A-70ACEED78C09","cleanprotonym":"Empis caucasipennipes Kustov & Shamshev, 2014","NomenclaturalCode":"ICZN"},{"tnuuuid":"EE0B8423-504B-43DC-90FE-4F4862DF4638","OriginalReferenceUUID":"5CDD59D4-8479-4C76-B689-DDC80C5B10B0","protonymuuid":"EE0B8423-504B-43DC-90FE-4F4862DF4638","label":"ladae 2014","value":"ladae 2014","lsid":"urn:lsid:zoobank.org:act:EE0B8423-504B-43DC-90FE-4F4862DF4638","parentname":"Empis Linn\u00e6us, 1758","namestring":"ladae","rankgroup":"Species","usageauthors":"","taxonnamerankid":"70","parentusageuuid":"A0020B63-C2AA-4203-847A-70ACEED78C09","cleanprotonym":"Empis ladae Kustov & Shamshev, 2014","NomenclaturalCode":"ICZN"},{"tnuuuid":"6CAD67CF-0221-4A7B-96B1-CF2699C2B83B","OriginalReferenceUUID":"5CDD59D4-8479-4C76-B689-DDC80C5B10B0","protonymuuid":"6CAD67CF-0221-4A7B-96B1-CF2699C2B83B","label":"longiphallus 2014","value":"longiphallus 2014","lsid":"urn:lsid:zoobank.org:act:6CAD67CF-0221-4A7B-96B1-CF2699C2B83B","parentname":"Empis Linn\u00e6us, 1758","namestring":"longiphallus","rankgroup":"Species","usageauthors":"","taxonnamerankid":"70","parentusageuuid":"A0020B63-C2AA-4203-847A-70ACEED78C09","cleanprotonym":"Empis longiphallus Kustov & Shamshev, 2014","NomenclaturalCode":"ICZN"}]}