{"referenceuuid":"B06419C3-E7F8-47B1-947C-7E7BFEF8AE28","label":"Fowler, Henry W.  1932. Notes on fresh water fishes from Central America. Proceedings of the Academy of Natural Sciences of Philadelphia 84: 379-385.","value":"Fowler, Henry W.  1932. Notes on fresh water fishes from Central America. Proceedings of the Academy of Natural Sciences of Philadelphia 84: 379-385.","authorlist":"Fowler, Henry W.","year":"1932","title":"Notes on fresh water fishes from Central America","citationdetails":"<em>Proceedings of the Academy of Natural Sciences of Philadelphia<\/em> <b>84<\/b>: 379-385.","volume":"84","number":"","edition":"","publisher":"","placepublished":"","pagination":"379-385","startpage":"379","endpage":"385","language":"","languageid":"0","referencetype":"Journal Article","lsid":"urn:lsid:zoobank.org:pub:B06419C3-E7F8-47B1-947C-7E7BFEF8AE28","parentreferenceid":"E69C08C0-DA92-4AD2-B656-B3DCECFBF0C1","parentreference":"Proceedings of the Academy of Natural Sciences of Philadelphia,  (Proc. Acad. Nat. Sci. Phila.)","authors":[[{"familyname":"Fowler","givenname":"Henry Weed","gnubuuid":"9C4FDCAF-D555-4A6A-9268-0DA2D1A354E0"}]],"NomenclaturalActs":[{"tnuuuid":"97ADB91F-1075-497E-BEC0-F16F23895CE8","OriginalReferenceUUID":"","protonymuuid":"6F79643A-C927-46DB-A3EA-12D4238B2A33","label":"Cyprinodontidae  [placeholder record]","value":"Cyprinodontidae  [placeholder record]","lsid":"","parentname":"","namestring":"Cyprinodontidae","rankgroup":"Family","usageauthors":"Fowler","taxonnamerankid":"50","parentusageuuid":"","cleanprotonym":"Cyprinodontidae","NomenclaturalCode":"ICZN"},{"tnuuuid":"1D23ED22-90F2-4967-880E-A68EB2C3D5C1","OriginalReferenceUUID":"69CFC6FB-CC14-42C4-9E4E-0A4D1A89DFF7","protonymuuid":"2D5E18F7-A978-4A06-8907-A1F0233A2D39","label":"Cichlasoma Swainson 1839","value":"Cichlasoma Swainson 1839","lsid":"urn:lsid:zoobank.org:act:2D5E18F7-A978-4A06-8907-A1F0233A2D39","parentname":"","namestring":"Cichlasoma","rankgroup":"Genus","usageauthors":"Fowler","taxonnamerankid":"60","parentusageuuid":"","cleanprotonym":"Plesiops (Cichlasoma) Swainson, 1839","NomenclaturalCode":"ICZN"},{"tnuuuid":"33CD497F-4958-4E21-B567-0480FF5D3F8B","OriginalReferenceUUID":"ABFF1855-0DFA-4E16-A40D-987B42146FBB","protonymuuid":"28BE8220-6AA0-429C-A866-B2AC97023E29","label":"Panamichthys Hubbs 1924","value":"Panamichthys Hubbs 1924","lsid":"urn:lsid:zoobank.org:act:28BE8220-6AA0-429C-A866-B2AC97023E29","parentname":"","namestring":"Panamichthys","rankgroup":"Genus","usageauthors":"Fowler","taxonnamerankid":"60","parentusageuuid":"","cleanprotonym":"Panamichthys Hubbs, 1924","NomenclaturalCode":"ICZN"},{"tnuuuid":"F3FD89F9-F3A9-42E4-98A1-CE34642D5A42","OriginalReferenceUUID":"57F81E6E-498C-48A0-B81F-CD2A943DE346","protonymuuid":"833E71ED-A4EF-4684-8D4D-CAAF955D965F","label":"Rhamdia Bleeker 1858","value":"Rhamdia Bleeker 1858","lsid":"urn:lsid:zoobank.org:act:833E71ED-A4EF-4684-8D4D-CAAF955D965F","parentname":"","namestring":"Rhamdia","rankgroup":"Genus","usageauthors":"Fowler","taxonnamerankid":"60","parentusageuuid":"","cleanprotonym":"Rhamdia Bleeker, 1858","NomenclaturalCode":"ICZN"},{"tnuuuid":"230C36DA-643C-4B5F-ADD0-11DA817D2CFE","OriginalReferenceUUID":"B06419C3-E7F8-47B1-947C-7E7BFEF8AE28","protonymuuid":"230C36DA-643C-4B5F-ADD0-11DA817D2CFE","label":"Plectrophallus Fowler 1932","value":"Plectrophallus Fowler 1932","lsid":"urn:lsid:zoobank.org:act:230C36DA-643C-4B5F-ADD0-11DA817D2CFE","parentname":"Panamichthys","namestring":"Plectrophallus","rankgroup":"Genus","usageauthors":"Fowler","taxonnamerankid":"63","parentusageuuid":"33CD497F-4958-4E21-B567-0480FF5D3F8B","cleanprotonym":"Panamichthys (Plectrophallus) Fowler, 1932","NomenclaturalCode":"ICZN"},{"tnuuuid":"AA1787B8-6C57-46B3-B745-27ED2F0BC0D8","OriginalReferenceUUID":"B06419C3-E7F8-47B1-947C-7E7BFEF8AE28","protonymuuid":"AA1787B8-6C57-46B3-B745-27ED2F0BC0D8","label":"cutteri Fowler 1932","value":"cutteri Fowler 1932","lsid":"urn:lsid:zoobank.org:act:AA1787B8-6C57-46B3-B745-27ED2F0BC0D8","parentname":"Cichlasoma","namestring":"cutteri","rankgroup":"Species","usageauthors":"Fowler","taxonnamerankid":"70","parentusageuuid":"1D23ED22-90F2-4967-880E-A68EB2C3D5C1","cleanprotonym":"Cichlasoma cutteri Fowler, 1932","NomenclaturalCode":"ICZN"},{"tnuuuid":"25958E50-E626-4B7C-956D-BA1FB7CE1F1E","OriginalReferenceUUID":"B06419C3-E7F8-47B1-947C-7E7BFEF8AE28","protonymuuid":"25958E50-E626-4B7C-956D-BA1FB7CE1F1E","label":"tristani Fowler 1932","value":"tristani Fowler 1932","lsid":"urn:lsid:zoobank.org:act:25958E50-E626-4B7C-956D-BA1FB7CE1F1E","parentname":"Panamichthys","namestring":"tristani","rankgroup":"Species","usageauthors":"Fowler","taxonnamerankid":"70","parentusageuuid":"33CD497F-4958-4E21-B567-0480FF5D3F8B","cleanprotonym":"Panamichthys tristani Fowler, 1932","NomenclaturalCode":"ICZN"},{"tnuuuid":"62572B9D-98D4-45C9-9F40-2E2189727265","OriginalReferenceUUID":"B06419C3-E7F8-47B1-947C-7E7BFEF8AE28","protonymuuid":"62572B9D-98D4-45C9-9F40-2E2189727265","label":"alfaroi Fowler 1932","value":"alfaroi Fowler 1932","lsid":"urn:lsid:zoobank.org:act:62572B9D-98D4-45C9-9F40-2E2189727265","parentname":"Rhamdia Bleeker, 1858","namestring":"alfaroi","rankgroup":"Species","usageauthors":"Fowler","taxonnamerankid":"70","parentusageuuid":"F3FD89F9-F3A9-42E4-98A1-CE34642D5A42","cleanprotonym":"Rhamdia alfaroi Fowler, 1932","NomenclaturalCode":"ICZN"}]}