{"referenceuuid":"9F2147ED-91CD-4025-BF99-BE8E95F06464","label":"Shaw, George.  1804. General zoology or systematic natural history .. [Unspecified Publisher] Vol. 5,  No. Parts 1-2: i-v, 1-25, i-vi, 251-463.","value":"Shaw, George.  1804. General zoology or systematic natural history .. [Unspecified Publisher] Vol. 5,  No. Parts 1-2: i-v, 1-25, i-vi, 251-463.","authorlist":"Shaw, George.","year":"1804","title":"General zoology or systematic natural history ...","citationdetails":"","volume":"5","number":"Parts 1-2","edition":"","publisher":"","placepublished":"","pagination":"i-v, 1-25, i-vi, 251-463, Pl. 93-132, 43+, 65+, 6+, 74+, 132-182, 158+","startpage":"","endpage":"","language":"","languageid":"0","referencetype":"Book","lsid":"urn:lsid:zoobank.org:pub:9F2147ED-91CD-4025-BF99-BE8E95F06464","parentreferenceid":"","parentreference":"","authors":[[{"familyname":"Shaw","givenname":"George","gnubuuid":"B48E25D0-0214-4624-8074-69A0656B1105"}]],"NomenclaturalActs":[{"tnuuuid":"A80EEFF1-0B57-4C21-A461-74E0C4F3E5FB","OriginalReferenceUUID":"2C6327E1-5560-4DB4-B9CA-76A0FA03D975","protonymuuid":"B4172EC3-0507-420B-9810-B1A2B8AB4FF2","label":"Balistes Linn\u00e6us 1758","value":"Balistes Linn\u00e6us 1758","lsid":"urn:lsid:zoobank.org:act:B4172EC3-0507-420B-9810-B1A2B8AB4FF2","parentname":"","namestring":"Balistes","rankgroup":"Genus","usageauthors":"Shaw","taxonnamerankid":"60","parentusageuuid":"","cleanprotonym":"Balistes Linn\u00e6us, 1758","NomenclaturalCode":"ICZN"},{"tnuuuid":"16D95213-87F3-4936-8E09-ABDCEF773EEB","OriginalReferenceUUID":"9F2147ED-91CD-4025-BF99-BE8E95F06464","protonymuuid":"16D95213-87F3-4936-8E09-ABDCEF773EEB","label":"Cephalus Shaw 1804","value":"Cephalus Shaw 1804","lsid":"urn:lsid:zoobank.org:act:16D95213-87F3-4936-8E09-ABDCEF773EEB","parentname":"","namestring":"Cephalus","rankgroup":"Genus","usageauthors":"Shaw","taxonnamerankid":"60","parentusageuuid":"","cleanprotonym":"Cephalus Shaw, 1804","NomenclaturalCode":"ICZN"},{"tnuuuid":"767077ED-0A87-412D-93C0-C162888BC908","OriginalReferenceUUID":"2C6327E1-5560-4DB4-B9CA-76A0FA03D975","protonymuuid":"731F0B54-DEED-4FA4-9EBF-3A4B78C09B33","label":"Chimaera Linn\u00e6us 1758","value":"Chimaera Linn\u00e6us 1758","lsid":"urn:lsid:zoobank.org:act:731F0B54-DEED-4FA4-9EBF-3A4B78C09B33","parentname":"","namestring":"Chimaera","rankgroup":"Genus","usageauthors":"Shaw","taxonnamerankid":"60","parentusageuuid":"","cleanprotonym":"Chim\u00e6ra Linn\u00e6us, 1758","NomenclaturalCode":"ICZN"},{"tnuuuid":"755B9621-F2F2-4237-98FB-B8F0E17FF8BE","OriginalReferenceUUID":"2C6327E1-5560-4DB4-B9CA-76A0FA03D975","protonymuuid":"B9EEA377-2471-438B-9126-FD7FA3ECFA8C","label":"Clupea Linn\u00e6us 1758","value":"Clupea Linn\u00e6us 1758","lsid":"urn:lsid:zoobank.org:act:B9EEA377-2471-438B-9126-FD7FA3ECFA8C","parentname":"","namestring":"Clupea","rankgroup":"Genus","usageauthors":"Shaw","taxonnamerankid":"60","parentusageuuid":"","cleanprotonym":"Clupea Linn\u00e6us, 1758","NomenclaturalCode":"ICZN"},{"tnuuuid":"D33A8349-0948-4C35-9392-6E39B21DEAAF","OriginalReferenceUUID":"2C6327E1-5560-4DB4-B9CA-76A0FA03D975","protonymuuid":"E39BA289-8606-4958-A96D-6D96C185B9F2","label":"Cyclopterus Linn\u00e6us 1758","value":"Cyclopterus Linn\u00e6us 1758","lsid":"urn:lsid:zoobank.org:act:E39BA289-8606-4958-A96D-6D96C185B9F2","parentname":"","namestring":"Cyclopterus","rankgroup":"Genus","usageauthors":"Shaw","taxonnamerankid":"60","parentusageuuid":"","cleanprotonym":"Cyclopterus Linn\u00e6us, 1758","NomenclaturalCode":"ICZN"},{"tnuuuid":"9C2E6D7C-2ABB-4A29-8FAD-6C73F517394E","OriginalReferenceUUID":"2C6327E1-5560-4DB4-B9CA-76A0FA03D975","protonymuuid":"4D9A0574-1D5E-4E6D-89EE-E3DC950BCC81","label":"Cyprinus Linn\u00e6us 1758","value":"Cyprinus Linn\u00e6us 1758","lsid":"urn:lsid:zoobank.org:act:4D9A0574-1D5E-4E6D-89EE-E3DC950BCC81","parentname":"","namestring":"Cyprinus","rankgroup":"Genus","usageauthors":"Shaw","taxonnamerankid":"60","parentusageuuid":"","cleanprotonym":"Cyprinus Linn\u00e6us, 1758","NomenclaturalCode":"ICZN"},{"tnuuuid":"8AE96BF6-D3F8-4339-A772-2D54D0846A9E","OriginalReferenceUUID":"2C6327E1-5560-4DB4-B9CA-76A0FA03D975","protonymuuid":"EFD61F13-AE18-42A7-864C-5660EA9492F2","label":"Diodon Linn\u00e6us 1758","value":"Diodon Linn\u00e6us 1758","lsid":"urn:lsid:zoobank.org:act:EFD61F13-AE18-42A7-864C-5660EA9492F2","parentname":"","namestring":"Diodon","rankgroup":"Genus","usageauthors":"Shaw & Lac\u00e9p\u00e8de in Shaw","taxonnamerankid":"60","parentusageuuid":"","cleanprotonym":"Diodon Linn\u00e6us, 1758","NomenclaturalCode":"ICZN"},{"tnuuuid":"60D0EB6C-4551-44E9-85CA-FB06D8CD0C27","OriginalReferenceUUID":"2C6327E1-5560-4DB4-B9CA-76A0FA03D975","protonymuuid":"14F7B916-4DB7-4C78-978B-E70E458F827F","label":"Esox Linn\u00e6us 1758","value":"Esox Linn\u00e6us 1758","lsid":"urn:lsid:zoobank.org:act:14F7B916-4DB7-4C78-978B-E70E458F827F","parentname":"","namestring":"Esox","rankgroup":"Genus","usageauthors":"Shaw","taxonnamerankid":"60","parentusageuuid":"","cleanprotonym":"Esox Linn\u00e6us, 1758","NomenclaturalCode":"ICZN"},{"tnuuuid":"AAD35906-1A8F-4775-AF1A-6C6A8DCC2E79","OriginalReferenceUUID":"1C890756-0824-4229-9EA6-9F65961750BC","protonymuuid":"62ECD2E2-032E-4524-A9FC-A4B6E24AAF20","label":"Gastrobranchus Bloch 1791","value":"Gastrobranchus Bloch 1791","lsid":"urn:lsid:zoobank.org:act:62ECD2E2-032E-4524-A9FC-A4B6E24AAF20","parentname":"","namestring":"Gastrobranchus","rankgroup":"Genus","usageauthors":"Shaw & Lac\u00e9p\u00e8de in Shaw","taxonnamerankid":"60","parentusageuuid":"","cleanprotonym":"Gastrobranchus Bloch, 1791","NomenclaturalCode":"ICZN"},{"tnuuuid":"F89794EC-F6CA-44B4-B1F2-4CA8D7336F9F","OriginalReferenceUUID":"2C6327E1-5560-4DB4-B9CA-76A0FA03D975","protonymuuid":"FDDA094A-D113-4F1A-A50B-482310300967","label":"Lophius Linn\u00e6us 1758","value":"Lophius Linn\u00e6us 1758","lsid":"urn:lsid:zoobank.org:act:FDDA094A-D113-4F1A-A50B-482310300967","parentname":"","namestring":"Lophius","rankgroup":"Genus","usageauthors":"Shaw","taxonnamerankid":"60","parentusageuuid":"","cleanprotonym":"Lophius Linn\u00e6us, 1758","NomenclaturalCode":"ICZN"},{"tnuuuid":"4FADEE49-D292-45B4-90EA-9E90094B0649","OriginalReferenceUUID":"2C6327E1-5560-4DB4-B9CA-76A0FA03D975","protonymuuid":"B3803885-682F-4807-A975-1839E719B4E5","label":"Loricaria Linn\u00e6us 1758","value":"Loricaria Linn\u00e6us 1758","lsid":"urn:lsid:zoobank.org:act:B3803885-682F-4807-A975-1839E719B4E5","parentname":"","namestring":"Loricaria","rankgroup":"Genus","usageauthors":"Shaw","taxonnamerankid":"60","parentusageuuid":"","cleanprotonym":"Loricaria Linn\u00e6us, 1758","NomenclaturalCode":"ICZN"},{"tnuuuid":"84EBEBF4-4374-4156-8AC8-6A787160CD5F","OriginalReferenceUUID":"2C6327E1-5560-4DB4-B9CA-76A0FA03D975","protonymuuid":"698C329F-25BA-481E-A768-3EC7246FF105","label":"Mullus Linn\u00e6us 1758","value":"Mullus Linn\u00e6us 1758","lsid":"urn:lsid:zoobank.org:act:698C329F-25BA-481E-A768-3EC7246FF105","parentname":"","namestring":"Mullus","rankgroup":"Genus","usageauthors":"Shaw","taxonnamerankid":"60","parentusageuuid":"","cleanprotonym":"Mullus Linn\u00e6us, 1758","NomenclaturalCode":"ICZN"},{"tnuuuid":"2F62D1CA-2E00-4AF6-BAF6-37513356B7F9","OriginalReferenceUUID":"2C6327E1-5560-4DB4-B9CA-76A0FA03D975","protonymuuid":"A2034307-721E-4D06-BD18-0E8692C7D17F","label":"Ostracion Linn\u00e6us 1758","value":"Ostracion Linn\u00e6us 1758","lsid":"urn:lsid:zoobank.org:act:A2034307-721E-4D06-BD18-0E8692C7D17F","parentname":"","namestring":"Ostracion","rankgroup":"Genus","usageauthors":"Shaw","taxonnamerankid":"60","parentusageuuid":"","cleanprotonym":"Ostracion Linn\u00e6us, 1758","NomenclaturalCode":"ICZN"},{"tnuuuid":"EFDB8F93-3932-4C59-83D2-1C233CA68190","OriginalReferenceUUID":"2C6327E1-5560-4DB4-B9CA-76A0FA03D975","protonymuuid":"65DF4FAD-7BD3-4094-94E4-73B24AE7C6E7","label":"Pegasus Linn\u00e6us 1758","value":"Pegasus Linn\u00e6us 1758","lsid":"urn:lsid:zoobank.org:act:65DF4FAD-7BD3-4094-94E4-73B24AE7C6E7","parentname":"","namestring":"Pegasus","rankgroup":"Genus","usageauthors":"Shaw","taxonnamerankid":"60","parentusageuuid":"","cleanprotonym":"Pegasus Linn\u00e6us, 1758","NomenclaturalCode":"ICZN"},{"tnuuuid":"06831D06-0503-4145-BB07-BC304F96131A","OriginalReferenceUUID":"2C6327E1-5560-4DB4-B9CA-76A0FA03D975","protonymuuid":"A0F4855F-39A0-446F-A654-16875AAD8EF7","label":"Petromyzon Linn\u00e6us 1758","value":"Petromyzon Linn\u00e6us 1758","lsid":"urn:lsid:zoobank.org:act:A0F4855F-39A0-446F-A654-16875AAD8EF7","parentname":"","namestring":"Petromyzon","rankgroup":"Genus","usageauthors":"Shaw","taxonnamerankid":"60","parentusageuuid":"","cleanprotonym":"Petromyzon Linn\u00e6us, 1758","NomenclaturalCode":"ICZN"},{"tnuuuid":"EF0693FD-5D3D-401D-88B4-067F3D6F276F","OriginalReferenceUUID":"2C6327E1-5560-4DB4-B9CA-76A0FA03D975","protonymuuid":"5A7C05A9-F4F2-48BF-9D58-56248EAB786C","label":"Polynemus Linn\u00e6us 1758","value":"Polynemus Linn\u00e6us 1758","lsid":"urn:lsid:zoobank.org:act:5A7C05A9-F4F2-48BF-9D58-56248EAB786C","parentname":"","namestring":"Polynemus","rankgroup":"Genus","usageauthors":"Shaw","taxonnamerankid":"60","parentusageuuid":"","cleanprotonym":"Polynemus Linn\u00e6us, 1758","NomenclaturalCode":"ICZN"},{"tnuuuid":"D195C227-EF46-4573-B38A-6FC7A313871A","OriginalReferenceUUID":"09892ACA-CF36-498B-8C7D-BAFDAF9E0423","protonymuuid":"B865A005-F1DE-4C23-BA3D-BFD3804C517A","label":"Polypterus Lac\u00e9p\u00e8de 1803","value":"Polypterus Lac\u00e9p\u00e8de 1803","lsid":"urn:lsid:zoobank.org:act:B865A005-F1DE-4C23-BA3D-BFD3804C517A","parentname":"","namestring":"Polypterus","rankgroup":"Genus","usageauthors":"Shaw","taxonnamerankid":"60","parentusageuuid":"","cleanprotonym":"Polypterus Lac\u00e9p\u00e8de, 1803","NomenclaturalCode":"ICZN"},{"tnuuuid":"4EA0752C-4C13-48F6-AB68-51AADE1D5026","OriginalReferenceUUID":"2C6327E1-5560-4DB4-B9CA-76A0FA03D975","protonymuuid":"8421A850-7ABC-4383-A02A-E7E22ABA4DEB","label":"Raja Linn\u00e6us 1758","value":"Raja Linn\u00e6us 1758","lsid":"urn:lsid:zoobank.org:act:8421A850-7ABC-4383-A02A-E7E22ABA4DEB","parentname":"","namestring":"Raja","rankgroup":"Genus","usageauthors":"Shaw","taxonnamerankid":"60","parentusageuuid":"","cleanprotonym":"Raja Linn\u00e6us, 1758","NomenclaturalCode":"ICZN"},{"tnuuuid":"0B9B48E2-71D4-4858-ABDB-962DDF389A66","OriginalReferenceUUID":"2C6327E1-5560-4DB4-B9CA-76A0FA03D975","protonymuuid":"6D02825F-7E9C-42E7-BD66-236B1C637326","label":"Salmo Linn\u00e6us 1758","value":"Salmo Linn\u00e6us 1758","lsid":"urn:lsid:zoobank.org:act:6D02825F-7E9C-42E7-BD66-236B1C637326","parentname":"","namestring":"Salmo","rankgroup":"Genus","usageauthors":"Shaw","taxonnamerankid":"60","parentusageuuid":"","cleanprotonym":"Salmo Linn\u00e6us, 1758","NomenclaturalCode":"ICZN"},{"tnuuuid":"2AAC6402-6AF5-493D-B87E-B93691ABF716","OriginalReferenceUUID":"9F2147ED-91CD-4025-BF99-BE8E95F06464","protonymuuid":"2AAC6402-6AF5-493D-B87E-B93691ABF716","label":"Spatularia Shaw 1804","value":"Spatularia Shaw 1804","lsid":"urn:lsid:zoobank.org:act:2AAC6402-6AF5-493D-B87E-B93691ABF716","parentname":"","namestring":"Spatularia","rankgroup":"Genus","usageauthors":"Shaw","taxonnamerankid":"60","parentusageuuid":"","cleanprotonym":"Spatularia Shaw, 1804","NomenclaturalCode":"ICZN"},{"tnuuuid":"2C3AC7A1-1270-4E23-A5F6-0BAC1D351D05","OriginalReferenceUUID":"2C6327E1-5560-4DB4-B9CA-76A0FA03D975","protonymuuid":"27C908C9-6E54-4E19-AF92-7635023DAAF6","label":"Squalus Linn\u00e6us 1758","value":"Squalus Linn\u00e6us 1758","lsid":"urn:lsid:zoobank.org:act:27C908C9-6E54-4E19-AF92-7635023DAAF6","parentname":"","namestring":"Squalus","rankgroup":"Genus","usageauthors":"Shaw","taxonnamerankid":"60","parentusageuuid":"","cleanprotonym":"Squalus Linn\u00e6us, 1758","NomenclaturalCode":"ICZN"},{"tnuuuid":"33D73D60-0320-4C4E-B7D2-750850C1E302","OriginalReferenceUUID":"2C6327E1-5560-4DB4-B9CA-76A0FA03D975","protonymuuid":"82686DD7-1938-4F92-9D39-45AEA37A35F8","label":"Syngnathus Linn\u00e6us 1758","value":"Syngnathus Linn\u00e6us 1758","lsid":"urn:lsid:zoobank.org:act:82686DD7-1938-4F92-9D39-45AEA37A35F8","parentname":"","namestring":"Syngnathus","rankgroup":"Genus","usageauthors":"Shaw","taxonnamerankid":"60","parentusageuuid":"","cleanprotonym":"Syngnathus Linn\u00e6us, 1758","NomenclaturalCode":"ICZN"},{"tnuuuid":"3F46C42D-0D73-40C3-8423-0CE6C9A4AA29","OriginalReferenceUUID":"2C6327E1-5560-4DB4-B9CA-76A0FA03D975","protonymuuid":"462B5444-A9F0-47CB-8008-A2089888F04E","label":"Tetrodon Linn\u00e6us 1758","value":"Tetrodon Linn\u00e6us 1758","lsid":"urn:lsid:zoobank.org:act:462B5444-A9F0-47CB-8008-A2089888F04E","parentname":"","namestring":"Tetrodon","rankgroup":"Genus","usageauthors":"Shaw","taxonnamerankid":"60","parentusageuuid":"","cleanprotonym":"Tetraodon Linn\u00e6us, 1758","NomenclaturalCode":"ICZN"},{"tnuuuid":"70E27E6C-F913-4690-BEBE-56C45F4A71B0","OriginalReferenceUUID":"9F2147ED-91CD-4025-BF99-BE8E95F06464","protonymuuid":"70E27E6C-F913-4690-BEBE-56C45F4A71B0","label":"bicolor Shaw 1804","value":"bicolor Shaw 1804","lsid":"urn:lsid:zoobank.org:act:70E27E6C-F913-4690-BEBE-56C45F4A71B0","parentname":"Balistes","namestring":"bicolor","rankgroup":"Species","usageauthors":"Shaw","taxonnamerankid":"70","parentusageuuid":"A80EEFF1-0B57-4C21-A461-74E0C4F3E5FB","cleanprotonym":"Balistes bicolor Shaw, 1804","NomenclaturalCode":"ICZN"},{"tnuuuid":"C71E5F44-C9A0-47B7-82B5-0F9D60F46B20","OriginalReferenceUUID":"9F2147ED-91CD-4025-BF99-BE8E95F06464","protonymuuid":"C71E5F44-C9A0-47B7-82B5-0F9D60F46B20","label":"capistratus Shaw 1804","value":"capistratus Shaw 1804","lsid":"urn:lsid:zoobank.org:act:C71E5F44-C9A0-47B7-82B5-0F9D60F46B20","parentname":"Balistes","namestring":"capistratus","rankgroup":"Species","usageauthors":"Shaw","taxonnamerankid":"70","parentusageuuid":"A80EEFF1-0B57-4C21-A461-74E0C4F3E5FB","cleanprotonym":"Balistes capistratus Shaw, 1804","NomenclaturalCode":"ICZN"},{"tnuuuid":"29952398-ECE8-40FD-B501-B846601DC430","OriginalReferenceUUID":"9F2147ED-91CD-4025-BF99-BE8E95F06464","protonymuuid":"29952398-ECE8-40FD-B501-B846601DC430","label":"fasciatus Shaw 1804","value":"fasciatus Shaw 1804","lsid":"urn:lsid:zoobank.org:act:29952398-ECE8-40FD-B501-B846601DC430","parentname":"Balistes","namestring":"fasciatus","rankgroup":"Species","usageauthors":"Shaw","taxonnamerankid":"70","parentusageuuid":"A80EEFF1-0B57-4C21-A461-74E0C4F3E5FB","cleanprotonym":"Balistes fasciatus Shaw, 1804","NomenclaturalCode":"ICZN"},{"tnuuuid":"E4A7706B-3E7B-474C-A4C8-FA1FE5241A60","OriginalReferenceUUID":"9F2147ED-91CD-4025-BF99-BE8E95F06464","protonymuuid":"E4A7706B-3E7B-474C-A4C8-FA1FE5241A60","label":"liturosus Shaw 1804","value":"liturosus Shaw 1804","lsid":"urn:lsid:zoobank.org:act:E4A7706B-3E7B-474C-A4C8-FA1FE5241A60","parentname":"Balistes","namestring":"liturosus","rankgroup":"Species","usageauthors":"Shaw","taxonnamerankid":"70","parentusageuuid":"A80EEFF1-0B57-4C21-A461-74E0C4F3E5FB","cleanprotonym":"Balistes liturosus Shaw, 1804","NomenclaturalCode":"ICZN"},{"tnuuuid":"E61FDACA-9977-4405-A622-2956B06B9533","OriginalReferenceUUID":"9F2147ED-91CD-4025-BF99-BE8E95F06464","protonymuuid":"E61FDACA-9977-4405-A622-2956B06B9533","label":"signatus Shaw 1804","value":"signatus Shaw 1804","lsid":"urn:lsid:zoobank.org:act:E61FDACA-9977-4405-A622-2956B06B9533","parentname":"Balistes","namestring":"signatus","rankgroup":"Species","usageauthors":"Shaw","taxonnamerankid":"70","parentusageuuid":"A80EEFF1-0B57-4C21-A461-74E0C4F3E5FB","cleanprotonym":"Balistes signatus Shaw, 1804","NomenclaturalCode":"ICZN"},{"tnuuuid":"8C5CC72C-05D4-4BA7-9581-59DDEB5AED3D","OriginalReferenceUUID":"9F2147ED-91CD-4025-BF99-BE8E95F06464","protonymuuid":"8C5CC72C-05D4-4BA7-9581-59DDEB5AED3D","label":"sonneratii Shaw 1804","value":"sonneratii Shaw 1804","lsid":"urn:lsid:zoobank.org:act:8C5CC72C-05D4-4BA7-9581-59DDEB5AED3D","parentname":"Balistes","namestring":"sonneratii","rankgroup":"Species","usageauthors":"Shaw","taxonnamerankid":"70","parentusageuuid":"A80EEFF1-0B57-4C21-A461-74E0C4F3E5FB","cleanprotonym":"Balistes sonneratii Shaw, 1804","NomenclaturalCode":"ICZN"},{"tnuuuid":"5B8A1B9A-ED25-4A90-A6EE-302EBF533600","OriginalReferenceUUID":"9F2147ED-91CD-4025-BF99-BE8E95F06464","protonymuuid":"5B8A1B9A-ED25-4A90-A6EE-302EBF533600","label":"unimaculatus Shaw 1804","value":"unimaculatus Shaw 1804","lsid":"urn:lsid:zoobank.org:act:5B8A1B9A-ED25-4A90-A6EE-302EBF533600","parentname":"Balistes","namestring":"unimaculatus","rankgroup":"Species","usageauthors":"Shaw","taxonnamerankid":"70","parentusageuuid":"A80EEFF1-0B57-4C21-A461-74E0C4F3E5FB","cleanprotonym":"Balistes unimaculatus Shaw, 1804","NomenclaturalCode":"ICZN"},{"tnuuuid":"81C6FAB9-211A-471F-A1A0-1374E8059A81","OriginalReferenceUUID":"9F2147ED-91CD-4025-BF99-BE8E95F06464","protonymuuid":"81C6FAB9-211A-471F-A1A0-1374E8059A81","label":"virescens Shaw 1804","value":"virescens Shaw 1804","lsid":"urn:lsid:zoobank.org:act:81C6FAB9-211A-471F-A1A0-1374E8059A81","parentname":"Balistes","namestring":"virescens","rankgroup":"Species","usageauthors":"Shaw","taxonnamerankid":"70","parentusageuuid":"A80EEFF1-0B57-4C21-A461-74E0C4F3E5FB","cleanprotonym":"Balistes virescens Shaw, 1804","NomenclaturalCode":"ICZN"},{"tnuuuid":"2DD2B823-EAC7-4961-A041-ED3BF11FFA6D","OriginalReferenceUUID":"9F2147ED-91CD-4025-BF99-BE8E95F06464","protonymuuid":"2DD2B823-EAC7-4961-A041-ED3BF11FFA6D","label":"brevis Shaw 1804","value":"brevis Shaw 1804","lsid":"urn:lsid:zoobank.org:act:2DD2B823-EAC7-4961-A041-ED3BF11FFA6D","parentname":"Cephalus","namestring":"brevis","rankgroup":"Species","usageauthors":"Shaw","taxonnamerankid":"70","parentusageuuid":"16D95213-87F3-4936-8E09-ABDCEF773EEB","cleanprotonym":"Cephalus brevis Shaw, 1804","NomenclaturalCode":"ICZN"},{"tnuuuid":"FA18D03C-3308-4387-8EA4-96294689324F","OriginalReferenceUUID":"9F2147ED-91CD-4025-BF99-BE8E95F06464","protonymuuid":"FA18D03C-3308-4387-8EA4-96294689324F","label":"oblongus Shaw 1804","value":"oblongus Shaw 1804","lsid":"urn:lsid:zoobank.org:act:FA18D03C-3308-4387-8EA4-96294689324F","parentname":"Cephalus","namestring":"oblongus","rankgroup":"Species","usageauthors":"Shaw","taxonnamerankid":"70","parentusageuuid":"16D95213-87F3-4936-8E09-ABDCEF773EEB","cleanprotonym":"Cephalus oblongus Shaw, 1804","NomenclaturalCode":"ICZN"},{"tnuuuid":"13A19444-9B53-4077-AFDF-2FC66492C74E","OriginalReferenceUUID":"9F2147ED-91CD-4025-BF99-BE8E95F06464","protonymuuid":"13A19444-9B53-4077-AFDF-2FC66492C74E","label":"pallasianus Shaw 1804","value":"pallasianus Shaw 1804","lsid":"urn:lsid:zoobank.org:act:13A19444-9B53-4077-AFDF-2FC66492C74E","parentname":"Cephalus","namestring":"pallasianus","rankgroup":"Species","usageauthors":"Shaw","taxonnamerankid":"70","parentusageuuid":"16D95213-87F3-4936-8E09-ABDCEF773EEB","cleanprotonym":"Cephalus pallasianus Shaw, 1804","NomenclaturalCode":"ICZN"},{"tnuuuid":"20C3827E-528D-4D4C-9287-56C7A75E2C6E","OriginalReferenceUUID":"9F2147ED-91CD-4025-BF99-BE8E95F06464","protonymuuid":"20C3827E-528D-4D4C-9287-56C7A75E2C6E","label":"varius Shaw 1804","value":"varius Shaw 1804","lsid":"urn:lsid:zoobank.org:act:20C3827E-528D-4D4C-9287-56C7A75E2C6E","parentname":"Cephalus","namestring":"varius","rankgroup":"Species","usageauthors":"Shaw","taxonnamerankid":"70","parentusageuuid":"16D95213-87F3-4936-8E09-ABDCEF773EEB","cleanprotonym":"Cephalus varius Shaw, 1804","NomenclaturalCode":"ICZN"},{"tnuuuid":"711DA5D3-4D60-4886-B987-DE16761A5019","OriginalReferenceUUID":"9F2147ED-91CD-4025-BF99-BE8E95F06464","protonymuuid":"711DA5D3-4D60-4886-B987-DE16761A5019","label":"australis Shaw 1804","value":"australis Shaw 1804","lsid":"urn:lsid:zoobank.org:act:711DA5D3-4D60-4886-B987-DE16761A5019","parentname":"Chimaera","namestring":"australis","rankgroup":"Species","usageauthors":"Shaw","taxonnamerankid":"70","parentusageuuid":"767077ED-0A87-412D-93C0-C162888BC908","cleanprotonym":"Chimaera australis Shaw, 1804","NomenclaturalCode":"ICZN"},{"tnuuuid":"602A88D7-0446-498F-8B09-14F9860EB133","OriginalReferenceUUID":"9F2147ED-91CD-4025-BF99-BE8E95F06464","protonymuuid":"602A88D7-0446-498F-8B09-14F9860EB133","label":"borealis Shaw 1804","value":"borealis Shaw 1804","lsid":"urn:lsid:zoobank.org:act:602A88D7-0446-498F-8B09-14F9860EB133","parentname":"Chimaera","namestring":"borealis","rankgroup":"Species","usageauthors":"Shaw","taxonnamerankid":"70","parentusageuuid":"767077ED-0A87-412D-93C0-C162888BC908","cleanprotonym":"Chimaera borealis Shaw, 1804","NomenclaturalCode":"ICZN"},{"tnuuuid":"71879058-F8A7-4498-9E70-67A37C68235E","OriginalReferenceUUID":"9F2147ED-91CD-4025-BF99-BE8E95F06464","protonymuuid":"71879058-F8A7-4498-9E70-67A37C68235E","label":"gigantea Shaw 1804","value":"gigantea Shaw 1804","lsid":"urn:lsid:zoobank.org:act:71879058-F8A7-4498-9E70-67A37C68235E","parentname":"Clupea","namestring":"gigantea","rankgroup":"Species","usageauthors":"Shaw","taxonnamerankid":"70","parentusageuuid":"755B9621-F2F2-4237-98FB-B8F0E17FF8BE","cleanprotonym":"Clupea gigantea Shaw, 1804","NomenclaturalCode":"ICZN"},{"tnuuuid":"8F534C90-8B54-4392-B7CA-AA17D735BDBA","OriginalReferenceUUID":"9F2147ED-91CD-4025-BF99-BE8E95F06464","protonymuuid":"8F534C90-8B54-4392-B7CA-AA17D735BDBA","label":"bispinosus Shaw 1804","value":"bispinosus Shaw 1804","lsid":"urn:lsid:zoobank.org:act:8F534C90-8B54-4392-B7CA-AA17D735BDBA","parentname":"Cyclopterus","namestring":"bispinosus","rankgroup":"Species","usageauthors":"Shaw","taxonnamerankid":"70","parentusageuuid":"D33A8349-0948-4C35-9392-6E39B21DEAAF","cleanprotonym":"Cyclopterus bispinosus Shaw, 1804","NomenclaturalCode":"ICZN"},{"tnuuuid":"87F5E5FB-71E2-4E05-B446-DB755A03FAF0","OriginalReferenceUUID":"9F2147ED-91CD-4025-BF99-BE8E95F06464","protonymuuid":"87F5E5FB-71E2-4E05-B446-DB755A03FAF0","label":"cornubicus Shaw 1804","value":"cornubicus Shaw 1804","lsid":"urn:lsid:zoobank.org:act:87F5E5FB-71E2-4E05-B446-DB755A03FAF0","parentname":"Cyclopterus","namestring":"cornubicus","rankgroup":"Species","usageauthors":"Shaw","taxonnamerankid":"70","parentusageuuid":"D33A8349-0948-4C35-9392-6E39B21DEAAF","cleanprotonym":"Cyclopterus cornubicus Shaw, 1804","NomenclaturalCode":"ICZN"},{"tnuuuid":"23B4BB33-9C25-4174-879B-5A90B69F526B","OriginalReferenceUUID":"9F2147ED-91CD-4025-BF99-BE8E95F06464","protonymuuid":"23B4BB33-9C25-4174-879B-5A90B69F526B","label":"pyramidatus Shaw 1804","value":"pyramidatus Shaw 1804","lsid":"urn:lsid:zoobank.org:act:23B4BB33-9C25-4174-879B-5A90B69F526B","parentname":"Cyclopterus","namestring":"pyramidatus","rankgroup":"Species","usageauthors":"Shaw","taxonnamerankid":"70","parentusageuuid":"D33A8349-0948-4C35-9392-6E39B21DEAAF","cleanprotonym":"Cyclopterus pyramidatus Shaw, 1804","NomenclaturalCode":"ICZN"},{"tnuuuid":"651A6A85-0CD7-4463-AE00-F7B154F96184","OriginalReferenceUUID":"9F2147ED-91CD-4025-BF99-BE8E95F06464","protonymuuid":"651A6A85-0CD7-4463-AE00-F7B154F96184","label":"ferrugineus Shaw 1804","value":"ferrugineus Shaw 1804","lsid":"urn:lsid:zoobank.org:act:651A6A85-0CD7-4463-AE00-F7B154F96184","parentname":"Cyprinus","namestring":"ferrugineus","rankgroup":"Species","usageauthors":"Shaw","taxonnamerankid":"70","parentusageuuid":"9C2E6D7C-2ABB-4A29-8FAD-6C73F517394E","cleanprotonym":"Cyprinus ferrugineus Shaw, 1804","NomenclaturalCode":"ICZN"},{"tnuuuid":"9A084861-8E5E-4D39-8AE2-3F5E5944E440","OriginalReferenceUUID":"9F2147ED-91CD-4025-BF99-BE8E95F06464","protonymuuid":"9A084861-8E5E-4D39-8AE2-3F5E5944E440","label":"lancastriensis Shaw 1804","value":"lancastriensis Shaw 1804","lsid":"urn:lsid:zoobank.org:act:9A084861-8E5E-4D39-8AE2-3F5E5944E440","parentname":"Cyprinus","namestring":"lancastriensis","rankgroup":"Species","usageauthors":"Shaw","taxonnamerankid":"70","parentusageuuid":"9C2E6D7C-2ABB-4A29-8FAD-6C73F517394E","cleanprotonym":"Cyprinus lancastriensis Shaw, 1804","NomenclaturalCode":"ICZN"},{"tnuuuid":"F4456951-7644-46D4-87B5-BA85B11C12C2","OriginalReferenceUUID":"9F2147ED-91CD-4025-BF99-BE8E95F06464","protonymuuid":"F4456951-7644-46D4-87B5-BA85B11C12C2","label":"pomeranicus Shaw 1804","value":"pomeranicus Shaw 1804","lsid":"urn:lsid:zoobank.org:act:F4456951-7644-46D4-87B5-BA85B11C12C2","parentname":"Cyprinus","namestring":"pomeranicus","rankgroup":"Species","usageauthors":"Shaw","taxonnamerankid":"70","parentusageuuid":"9C2E6D7C-2ABB-4A29-8FAD-6C73F517394E","cleanprotonym":"Cyprinus pomeranicus Shaw, 1804","NomenclaturalCode":"ICZN"},{"tnuuuid":"82244B66-CD97-43CB-9380-EE1E0F203A46","OriginalReferenceUUID":"9F2147ED-91CD-4025-BF99-BE8E95F06464","protonymuuid":"82244B66-CD97-43CB-9380-EE1E0F203A46","label":"punctatus Shaw 1804","value":"punctatus Shaw 1804","lsid":"urn:lsid:zoobank.org:act:82244B66-CD97-43CB-9380-EE1E0F203A46","parentname":"Cyprinus","namestring":"punctatus","rankgroup":"Species","usageauthors":"Shaw","taxonnamerankid":"70","parentusageuuid":"9C2E6D7C-2ABB-4A29-8FAD-6C73F517394E","cleanprotonym":"Cyprinus punctatus Shaw, 1804","NomenclaturalCode":"ICZN"},{"tnuuuid":"75712D9F-CAA2-49A0-A822-336D77B293B3","OriginalReferenceUUID":"9F2147ED-91CD-4025-BF99-BE8E95F06464","protonymuuid":"75712D9F-CAA2-49A0-A822-336D77B293B3","label":"quadrilobus Shaw 1804","value":"quadrilobus Shaw 1804","lsid":"urn:lsid:zoobank.org:act:75712D9F-CAA2-49A0-A822-336D77B293B3","parentname":"Cyprinus","namestring":"quadrilobus","rankgroup":"Species","usageauthors":"Shaw","taxonnamerankid":"70","parentusageuuid":"9C2E6D7C-2ABB-4A29-8FAD-6C73F517394E","cleanprotonym":"Cyprinus quadrilobus Shaw, 1804","NomenclaturalCode":"ICZN"},{"tnuuuid":"A116CC18-88BA-4E45-95D9-8B2E3481D3D2","OriginalReferenceUUID":"9F2147ED-91CD-4025-BF99-BE8E95F06464","protonymuuid":"A116CC18-88BA-4E45-95D9-8B2E3481D3D2","label":"serta Shaw 1804","value":"serta Shaw 1804","lsid":"urn:lsid:zoobank.org:act:A116CC18-88BA-4E45-95D9-8B2E3481D3D2","parentname":"Cyprinus","namestring":"serta","rankgroup":"Species","usageauthors":"Shaw","taxonnamerankid":"70","parentusageuuid":"9C2E6D7C-2ABB-4A29-8FAD-6C73F517394E","cleanprotonym":"Cyprinus serta Shaw, 1804","NomenclaturalCode":"ICZN"},{"tnuuuid":"F6104661-5AA0-4BD3-A7AE-B0E094F42EEB","OriginalReferenceUUID":"9F2147ED-91CD-4025-BF99-BE8E95F06464","protonymuuid":"F6104661-5AA0-4BD3-A7AE-B0E094F42EEB","label":"tincaurea Shaw 1804","value":"tincaurea Shaw 1804","lsid":"urn:lsid:zoobank.org:act:F6104661-5AA0-4BD3-A7AE-B0E094F42EEB","parentname":"Cyprinus","namestring":"tincaurea","rankgroup":"Species","usageauthors":"Shaw","taxonnamerankid":"70","parentusageuuid":"9C2E6D7C-2ABB-4A29-8FAD-6C73F517394E","cleanprotonym":"Cyprinus tincaurea Shaw, 1804","NomenclaturalCode":"ICZN"},{"tnuuuid":"2CA0F46F-4BEA-4703-87A9-8B65D77E5700","OriginalReferenceUUID":"9F2147ED-91CD-4025-BF99-BE8E95F06464","protonymuuid":"2CA0F46F-4BEA-4703-87A9-8B65D77E5700","label":"liturosus Shaw & Lac\u00e9p\u00e8de in Shaw in Shaw 1804","value":"liturosus Shaw & Lac\u00e9p\u00e8de in Shaw in Shaw 1804","lsid":"urn:lsid:zoobank.org:act:2CA0F46F-4BEA-4703-87A9-8B65D77E5700","parentname":"Diodon","namestring":"liturosus","rankgroup":"Species","usageauthors":"Shaw & Lac\u00e9p\u00e8de in Shaw","taxonnamerankid":"70","parentusageuuid":"8AE96BF6-D3F8-4339-A772-2D54D0846A9E","cleanprotonym":"Diodon liturosus Shaw in Shaw, 1804","NomenclaturalCode":"ICZN"},{"tnuuuid":"24F300A7-46C8-4BB8-9BE3-A9422DF8DB48","OriginalReferenceUUID":"9F2147ED-91CD-4025-BF99-BE8E95F06464","protonymuuid":"24F300A7-46C8-4BB8-9BE3-A9422DF8DB48","label":"cepedianus Shaw 1804","value":"cepedianus Shaw 1804","lsid":"urn:lsid:zoobank.org:act:24F300A7-46C8-4BB8-9BE3-A9422DF8DB48","parentname":"Esox","namestring":"cepedianus","rankgroup":"Species","usageauthors":"Shaw","taxonnamerankid":"70","parentusageuuid":"60D0EB6C-4551-44E9-85CA-FB06D8CD0C27","cleanprotonym":"Esox cepedianus Shaw, 1804","NomenclaturalCode":"ICZN"},{"tnuuuid":"67DC47E4-44FD-4B59-B486-612F40933854","OriginalReferenceUUID":"9F2147ED-91CD-4025-BF99-BE8E95F06464","protonymuuid":"67DC47E4-44FD-4B59-B486-612F40933854","label":"dombeyi Shaw & Lac\u00e9p\u00e8de in Shaw in Shaw 1804","value":"dombeyi Shaw & Lac\u00e9p\u00e8de in Shaw in Shaw 1804","lsid":"urn:lsid:zoobank.org:act:67DC47E4-44FD-4B59-B486-612F40933854","parentname":"Gastrobranchus","namestring":"dombeyi","rankgroup":"Species","usageauthors":"Shaw & Lac\u00e9p\u00e8de in Shaw","taxonnamerankid":"70","parentusageuuid":"AAD35906-1A8F-4775-AF1A-6C6A8DCC2E79","cleanprotonym":"Gastrobranchus dombeyi Shaw in Shaw, 1804","NomenclaturalCode":"ICZN"},{"tnuuuid":"60E7A52E-506A-4848-9CD0-06FCD36A30C0","OriginalReferenceUUID":"9F2147ED-91CD-4025-BF99-BE8E95F06464","protonymuuid":"60E7A52E-506A-4848-9CD0-06FCD36A30C0","label":"commersonii Shaw 1804","value":"commersonii Shaw 1804","lsid":"urn:lsid:zoobank.org:act:60E7A52E-506A-4848-9CD0-06FCD36A30C0","parentname":"Lophius","namestring":"commersonii","rankgroup":"Species","usageauthors":"Shaw","taxonnamerankid":"70","parentusageuuid":"F89794EC-F6CA-44B4-B1F2-4CA8D7336F9F","cleanprotonym":"Lophius commersonii Shaw, 1804","NomenclaturalCode":"ICZN"},{"tnuuuid":"CA5440E1-6EAD-4389-829D-3D3031FAB836","OriginalReferenceUUID":"9F2147ED-91CD-4025-BF99-BE8E95F06464","protonymuuid":"CA5440E1-6EAD-4389-829D-3D3031FAB836","label":"cornubicus Shaw 1804","value":"cornubicus Shaw 1804","lsid":"urn:lsid:zoobank.org:act:CA5440E1-6EAD-4389-829D-3D3031FAB836","parentname":"Lophius","namestring":"cornubicus","rankgroup":"Species","usageauthors":"Shaw","taxonnamerankid":"70","parentusageuuid":"F89794EC-F6CA-44B4-B1F2-4CA8D7336F9F","cleanprotonym":"Lophius cornubicus Shaw, 1804","NomenclaturalCode":"ICZN"},{"tnuuuid":"6376FED2-85AE-4E62-B3F6-8179F8913142","OriginalReferenceUUID":"9F2147ED-91CD-4025-BF99-BE8E95F06464","protonymuuid":"6376FED2-85AE-4E62-B3F6-8179F8913142","label":"europaeus Shaw 1804","value":"europaeus Shaw 1804","lsid":"urn:lsid:zoobank.org:act:6376FED2-85AE-4E62-B3F6-8179F8913142","parentname":"Lophius","namestring":"europaeus","rankgroup":"Species","usageauthors":"Shaw","taxonnamerankid":"70","parentusageuuid":"F89794EC-F6CA-44B4-B1F2-4CA8D7336F9F","cleanprotonym":"Lophius europaeus Shaw, 1804","NomenclaturalCode":"ICZN"},{"tnuuuid":"6823C76B-1245-4DA2-8CDB-6E6A0B91B771","OriginalReferenceUUID":"9F2147ED-91CD-4025-BF99-BE8E95F06464","protonymuuid":"6823C76B-1245-4DA2-8CDB-6E6A0B91B771","label":"muricatus Shaw 1804","value":"muricatus Shaw 1804","lsid":"urn:lsid:zoobank.org:act:6823C76B-1245-4DA2-8CDB-6E6A0B91B771","parentname":"Lophius","namestring":"muricatus","rankgroup":"Species","usageauthors":"Shaw","taxonnamerankid":"70","parentusageuuid":"F89794EC-F6CA-44B4-B1F2-4CA8D7336F9F","cleanprotonym":"Lophius muricatus Shaw, 1804","NomenclaturalCode":"ICZN"},{"tnuuuid":"36923724-0C6F-4DB5-BC50-02849C3B9A0B","OriginalReferenceUUID":"9F2147ED-91CD-4025-BF99-BE8E95F06464","protonymuuid":"36923724-0C6F-4DB5-BC50-02849C3B9A0B","label":"rostratus Shaw 1804","value":"rostratus Shaw 1804","lsid":"urn:lsid:zoobank.org:act:36923724-0C6F-4DB5-BC50-02849C3B9A0B","parentname":"Lophius","namestring":"rostratus","rankgroup":"Species","usageauthors":"Shaw","taxonnamerankid":"70","parentusageuuid":"F89794EC-F6CA-44B4-B1F2-4CA8D7336F9F","cleanprotonym":"Lophius rostratus Shaw, 1804","NomenclaturalCode":"ICZN"},{"tnuuuid":"E9D76BF2-9BFD-43B1-A1F7-64CFE9C7F026","OriginalReferenceUUID":"9F2147ED-91CD-4025-BF99-BE8E95F06464","protonymuuid":"E9D76BF2-9BFD-43B1-A1F7-64CFE9C7F026","label":"accipenser Shaw 1804","value":"accipenser Shaw 1804","lsid":"urn:lsid:zoobank.org:act:E9D76BF2-9BFD-43B1-A1F7-64CFE9C7F026","parentname":"Loricaria","namestring":"accipenser","rankgroup":"Species","usageauthors":"Shaw","taxonnamerankid":"70","parentusageuuid":"4FADEE49-D292-45B4-90EA-9E90094B0649","cleanprotonym":"Loricaria accipenser Shaw, 1804","NomenclaturalCode":"ICZN"},{"tnuuuid":"98D29F57-F633-4FC1-91FE-25924C50BC72","OriginalReferenceUUID":"9F2147ED-91CD-4025-BF99-BE8E95F06464","protonymuuid":"98D29F57-F633-4FC1-91FE-25924C50BC72","label":"dentata Shaw 1804","value":"dentata Shaw 1804","lsid":"urn:lsid:zoobank.org:act:98D29F57-F633-4FC1-91FE-25924C50BC72","parentname":"Loricaria","namestring":"dentata","rankgroup":"Species","usageauthors":"Shaw","taxonnamerankid":"70","parentusageuuid":"4FADEE49-D292-45B4-90EA-9E90094B0649","cleanprotonym":"Loricaria dentata Shaw, 1804","NomenclaturalCode":"ICZN"},{"tnuuuid":"80AD5352-C262-450F-868A-37D49711799B","OriginalReferenceUUID":"9F2147ED-91CD-4025-BF99-BE8E95F06464","protonymuuid":"80AD5352-C262-450F-868A-37D49711799B","label":"flava Shaw 1804","value":"flava Shaw 1804","lsid":"urn:lsid:zoobank.org:act:80AD5352-C262-450F-868A-37D49711799B","parentname":"Loricaria","namestring":"flava","rankgroup":"Species","usageauthors":"Shaw","taxonnamerankid":"70","parentusageuuid":"4FADEE49-D292-45B4-90EA-9E90094B0649","cleanprotonym":"Loricaria flava Shaw, 1804","NomenclaturalCode":"ICZN"},{"tnuuuid":"359ADFA1-0384-44B5-8C66-E75E3F9485C1","OriginalReferenceUUID":"9F2147ED-91CD-4025-BF99-BE8E95F06464","protonymuuid":"359ADFA1-0384-44B5-8C66-E75E3F9485C1","label":"malabaricus Shaw 1804","value":"malabaricus Shaw 1804","lsid":"urn:lsid:zoobank.org:act:359ADFA1-0384-44B5-8C66-E75E3F9485C1","parentname":"Mullus","namestring":"malabaricus","rankgroup":"Species","usageauthors":"Shaw","taxonnamerankid":"70","parentusageuuid":"84EBEBF4-4374-4156-8AC8-6A787160CD5F","cleanprotonym":"Mullus malabaricus Shaw, 1804","NomenclaturalCode":"ICZN"},{"tnuuuid":"8CB92229-A0CE-4DE1-B134-5921CAD39E48","OriginalReferenceUUID":"9F2147ED-91CD-4025-BF99-BE8E95F06464","protonymuuid":"8CB92229-A0CE-4DE1-B134-5921CAD39E48","label":"striatus Shaw 1804","value":"striatus Shaw 1804","lsid":"urn:lsid:zoobank.org:act:8CB92229-A0CE-4DE1-B134-5921CAD39E48","parentname":"Ostracion","namestring":"striatus","rankgroup":"Species","usageauthors":"Shaw","taxonnamerankid":"70","parentusageuuid":"2F62D1CA-2E00-4AF6-BAF6-37513356B7F9","cleanprotonym":"Ostracion striatus Shaw, 1804","NomenclaturalCode":"ICZN"},{"tnuuuid":"33B5F44A-5663-415B-9BC4-DE09774865C9","OriginalReferenceUUID":"9F2147ED-91CD-4025-BF99-BE8E95F06464","protonymuuid":"33B5F44A-5663-415B-9BC4-DE09774865C9","label":"draco Shaw 1804","value":"draco Shaw 1804","lsid":"urn:lsid:zoobank.org:act:33B5F44A-5663-415B-9BC4-DE09774865C9","parentname":"Pegasus","namestring":"draco","rankgroup":"Species","usageauthors":"Shaw","taxonnamerankid":"70","parentusageuuid":"EFDB8F93-3932-4C59-83D2-1C233CA68190","cleanprotonym":"Pegasus draco Shaw, 1804","NomenclaturalCode":"ICZN"},{"tnuuuid":"D7058D6F-10D6-4C61-9974-6AFF832DA7CD","OriginalReferenceUUID":"9F2147ED-91CD-4025-BF99-BE8E95F06464","protonymuuid":"D7058D6F-10D6-4C61-9974-6AFF832DA7CD","label":"bicolor Shaw 1804","value":"bicolor Shaw 1804","lsid":"urn:lsid:zoobank.org:act:D7058D6F-10D6-4C61-9974-6AFF832DA7CD","parentname":"Petromyzon","namestring":"bicolor","rankgroup":"Species","usageauthors":"Shaw","taxonnamerankid":"70","parentusageuuid":"06831D06-0503-4145-BB07-BC304F96131A","cleanprotonym":"Petromyzon bicolor Shaw, 1804","NomenclaturalCode":"ICZN"},{"tnuuuid":"97F7BD1B-61EB-485B-B2AA-6154B0C44E1C","OriginalReferenceUUID":"9F2147ED-91CD-4025-BF99-BE8E95F06464","protonymuuid":"97F7BD1B-61EB-485B-B2AA-6154B0C44E1C","label":"plumbeus Shaw 1804","value":"plumbeus Shaw 1804","lsid":"urn:lsid:zoobank.org:act:97F7BD1B-61EB-485B-B2AA-6154B0C44E1C","parentname":"Petromyzon","namestring":"plumbeus","rankgroup":"Species","usageauthors":"Shaw","taxonnamerankid":"70","parentusageuuid":"06831D06-0503-4145-BB07-BC304F96131A","cleanprotonym":"Petromyzon plumbeus Shaw, 1804","NomenclaturalCode":"ICZN"},{"tnuuuid":"B3ED7CD6-3D27-4BAB-B134-24AF7F613EDA","OriginalReferenceUUID":"9F2147ED-91CD-4025-BF99-BE8E95F06464","protonymuuid":"B3ED7CD6-3D27-4BAB-B134-24AF7F613EDA","label":"commersonii Shaw 1804","value":"commersonii Shaw 1804","lsid":"urn:lsid:zoobank.org:act:B3ED7CD6-3D27-4BAB-B134-24AF7F613EDA","parentname":"Polynemus","namestring":"commersonii","rankgroup":"Species","usageauthors":"Shaw","taxonnamerankid":"70","parentusageuuid":"EF0693FD-5D3D-401D-88B4-067F3D6F276F","cleanprotonym":"Polynemus commersonii Shaw, 1804","NomenclaturalCode":"ICZN"},{"tnuuuid":"87F845D7-DA13-440C-9914-06F1524F612D","OriginalReferenceUUID":"9F2147ED-91CD-4025-BF99-BE8E95F06464","protonymuuid":"87F845D7-DA13-440C-9914-06F1524F612D","label":"indicus Shaw 1804","value":"indicus Shaw 1804","lsid":"urn:lsid:zoobank.org:act:87F845D7-DA13-440C-9914-06F1524F612D","parentname":"Polynemus","namestring":"indicus","rankgroup":"Species","usageauthors":"Shaw","taxonnamerankid":"70","parentusageuuid":"EF0693FD-5D3D-401D-88B4-067F3D6F276F","cleanprotonym":"Polynemus indicus Shaw, 1804","NomenclaturalCode":"ICZN"},{"tnuuuid":"65982A21-F2CE-4950-A4A0-84C2795FA4D6","OriginalReferenceUUID":"9F2147ED-91CD-4025-BF99-BE8E95F06464","protonymuuid":"65982A21-F2CE-4950-A4A0-84C2795FA4D6","label":"niloticus Shaw 1804","value":"niloticus Shaw 1804","lsid":"urn:lsid:zoobank.org:act:65982A21-F2CE-4950-A4A0-84C2795FA4D6","parentname":"Polynemus","namestring":"niloticus","rankgroup":"Species","usageauthors":"Shaw","taxonnamerankid":"70","parentusageuuid":"EF0693FD-5D3D-401D-88B4-067F3D6F276F","cleanprotonym":"Polynemus niloticus Shaw, 1804","NomenclaturalCode":"ICZN"},{"tnuuuid":"1624EEBB-EA58-4F9D-AE53-695E7EFEC219","OriginalReferenceUUID":"9F2147ED-91CD-4025-BF99-BE8E95F06464","protonymuuid":"1624EEBB-EA58-4F9D-AE53-695E7EFEC219","label":"tetradactylus Shaw 1804","value":"tetradactylus Shaw 1804","lsid":"urn:lsid:zoobank.org:act:1624EEBB-EA58-4F9D-AE53-695E7EFEC219","parentname":"Polynemus","namestring":"tetradactylus","rankgroup":"Species","usageauthors":"Shaw","taxonnamerankid":"70","parentusageuuid":"EF0693FD-5D3D-401D-88B4-067F3D6F276F","cleanprotonym":"Polynemus tetradactylus Shaw, 1804","NomenclaturalCode":"ICZN"},{"tnuuuid":"1EDD8DCC-F54C-49E1-A727-3E72656CCDDA","OriginalReferenceUUID":"9F2147ED-91CD-4025-BF99-BE8E95F06464","protonymuuid":"1EDD8DCC-F54C-49E1-A727-3E72656CCDDA","label":"niloticus Shaw 1804","value":"niloticus Shaw 1804","lsid":"urn:lsid:zoobank.org:act:1EDD8DCC-F54C-49E1-A727-3E72656CCDDA","parentname":"Polypterus","namestring":"niloticus","rankgroup":"Species","usageauthors":"Shaw","taxonnamerankid":"70","parentusageuuid":"D195C227-EF46-4573-B38A-6FC7A313871A","cleanprotonym":"Polypterus niloticus Shaw, 1804","NomenclaturalCode":"ICZN"},{"tnuuuid":"A713C903-5F3C-4BF2-BA08-7A2DECD3D438","OriginalReferenceUUID":"9F2147ED-91CD-4025-BF99-BE8E95F06464","protonymuuid":"A713C903-5F3C-4BF2-BA08-7A2DECD3D438","label":"bicolor Shaw 1804","value":"bicolor Shaw 1804","lsid":"urn:lsid:zoobank.org:act:A713C903-5F3C-4BF2-BA08-7A2DECD3D438","parentname":"Raja","namestring":"bicolor","rankgroup":"Species","usageauthors":"Shaw","taxonnamerankid":"70","parentusageuuid":"4EA0752C-4C13-48F6-AB68-51AADE1D5026","cleanprotonym":"Raja bicolor Shaw, 1804","NomenclaturalCode":"ICZN"},{"tnuuuid":"DC5953CE-BC8C-4097-A10E-239AC80EEC40","OriginalReferenceUUID":"9F2147ED-91CD-4025-BF99-BE8E95F06464","protonymuuid":"DC5953CE-BC8C-4097-A10E-239AC80EEC40","label":"chagrinea Shaw 1804","value":"chagrinea Shaw 1804","lsid":"urn:lsid:zoobank.org:act:DC5953CE-BC8C-4097-A10E-239AC80EEC40","parentname":"Raja","namestring":"chagrinea","rankgroup":"Species","usageauthors":"Shaw","taxonnamerankid":"70","parentusageuuid":"4EA0752C-4C13-48F6-AB68-51AADE1D5026","cleanprotonym":"Raja chagrinea Shaw, 1804","NomenclaturalCode":"ICZN"},{"tnuuuid":"965610E2-F890-4C33-8D3F-06B7EFF35A55","OriginalReferenceUUID":"9F2147ED-91CD-4025-BF99-BE8E95F06464","protonymuuid":"965610E2-F890-4C33-8D3F-06B7EFF35A55","label":"cuvieri Shaw 1804","value":"cuvieri Shaw 1804","lsid":"urn:lsid:zoobank.org:act:965610E2-F890-4C33-8D3F-06B7EFF35A55","parentname":"Raja","namestring":"cuvieri","rankgroup":"Species","usageauthors":"Shaw","taxonnamerankid":"70","parentusageuuid":"4EA0752C-4C13-48F6-AB68-51AADE1D5026","cleanprotonym":"Raja cuvieri Shaw, 1804","NomenclaturalCode":"ICZN"},{"tnuuuid":"AC787B33-95F8-4B98-ADC0-5E1F71B2C936","OriginalReferenceUUID":"9F2147ED-91CD-4025-BF99-BE8E95F06464","protonymuuid":"AC787B33-95F8-4B98-ADC0-5E1F71B2C936","label":"diabolus Shaw 1804","value":"diabolus Shaw 1804","lsid":"urn:lsid:zoobank.org:act:AC787B33-95F8-4B98-ADC0-5E1F71B2C936","parentname":"Raja","namestring":"diabolus","rankgroup":"Species","usageauthors":"Shaw","taxonnamerankid":"70","parentusageuuid":"4EA0752C-4C13-48F6-AB68-51AADE1D5026","cleanprotonym":"Raja diabolus Shaw, 1804","NomenclaturalCode":"ICZN"},{"tnuuuid":"359DFE88-9C13-48DF-AC82-28A26496A2B9","OriginalReferenceUUID":"9F2147ED-91CD-4025-BF99-BE8E95F06464","protonymuuid":"359DFE88-9C13-48DF-AC82-28A26496A2B9","label":"fasciata Shaw 1804","value":"fasciata Shaw 1804","lsid":"urn:lsid:zoobank.org:act:359DFE88-9C13-48DF-AC82-28A26496A2B9","parentname":"Raja","namestring":"fasciata","rankgroup":"Species","usageauthors":"Shaw","taxonnamerankid":"70","parentusageuuid":"4EA0752C-4C13-48F6-AB68-51AADE1D5026","cleanprotonym":"Raja fasciata Shaw, 1804","NomenclaturalCode":"ICZN"},{"tnuuuid":"CBC41E60-66D9-4874-BF89-98F88FB48FB4","OriginalReferenceUUID":"9F2147ED-91CD-4025-BF99-BE8E95F06464","protonymuuid":"CBC41E60-66D9-4874-BF89-98F88FB48FB4","label":"guttata Shaw 1804","value":"guttata Shaw 1804","lsid":"urn:lsid:zoobank.org:act:CBC41E60-66D9-4874-BF89-98F88FB48FB4","parentname":"Raja","namestring":"guttata","rankgroup":"Species","usageauthors":"Shaw","taxonnamerankid":"70","parentusageuuid":"4EA0752C-4C13-48F6-AB68-51AADE1D5026","cleanprotonym":"Raja guttata Shaw, 1804","NomenclaturalCode":"ICZN"},{"tnuuuid":"EB4DE614-E910-4BC8-B33B-A65DCA538425","OriginalReferenceUUID":"9F2147ED-91CD-4025-BF99-BE8E95F06464","protonymuuid":"EB4DE614-E910-4BC8-B33B-A65DCA538425","label":"maculata Shaw 1804","value":"maculata Shaw 1804","lsid":"urn:lsid:zoobank.org:act:EB4DE614-E910-4BC8-B33B-A65DCA538425","parentname":"Raja","namestring":"maculata","rankgroup":"Species","usageauthors":"Shaw","taxonnamerankid":"70","parentusageuuid":"4EA0752C-4C13-48F6-AB68-51AADE1D5026","cleanprotonym":"Raja maculata Shaw, 1804","NomenclaturalCode":"ICZN"},{"tnuuuid":"810A044A-0595-4CA9-8E01-EE802D4C4657","OriginalReferenceUUID":"9F2147ED-91CD-4025-BF99-BE8E95F06464","protonymuuid":"810A044A-0595-4CA9-8E01-EE802D4C4657","label":"poecilura Shaw 1804","value":"poecilura Shaw 1804","lsid":"urn:lsid:zoobank.org:act:810A044A-0595-4CA9-8E01-EE802D4C4657","parentname":"Raja","namestring":"poecilura","rankgroup":"Species","usageauthors":"Shaw","taxonnamerankid":"70","parentusageuuid":"4EA0752C-4C13-48F6-AB68-51AADE1D5026","cleanprotonym":"Raja poecilura Shaw, 1804","NomenclaturalCode":"ICZN"},{"tnuuuid":"04472683-3AE6-43A6-8D36-B1279C083185","OriginalReferenceUUID":"9F2147ED-91CD-4025-BF99-BE8E95F06464","protonymuuid":"04472683-3AE6-43A6-8D36-B1279C083185","label":"sinensis Shaw 1804","value":"sinensis Shaw 1804","lsid":"urn:lsid:zoobank.org:act:04472683-3AE6-43A6-8D36-B1279C083185","parentname":"Raja","namestring":"sinensis","rankgroup":"Species","usageauthors":"Shaw","taxonnamerankid":"70","parentusageuuid":"4EA0752C-4C13-48F6-AB68-51AADE1D5026","cleanprotonym":"Raja sinensis Shaw, 1804","NomenclaturalCode":"ICZN"},{"tnuuuid":"F1945180-19B5-4219-A051-C27F4BE415DC","OriginalReferenceUUID":"9F2147ED-91CD-4025-BF99-BE8E95F06464","protonymuuid":"F1945180-19B5-4219-A051-C27F4BE415DC","label":"thouiniana Shaw 1804","value":"thouiniana Shaw 1804","lsid":"urn:lsid:zoobank.org:act:F1945180-19B5-4219-A051-C27F4BE415DC","parentname":"Raja","namestring":"thouiniana","rankgroup":"Species","usageauthors":"Shaw","taxonnamerankid":"70","parentusageuuid":"4EA0752C-4C13-48F6-AB68-51AADE1D5026","cleanprotonym":"Raja thouiniana Shaw, 1804","NomenclaturalCode":"ICZN"},{"tnuuuid":"BFD7E681-9BC4-46A5-A916-EC19A1288C0F","OriginalReferenceUUID":"9F2147ED-91CD-4025-BF99-BE8E95F06464","protonymuuid":"BFD7E681-9BC4-46A5-A916-EC19A1288C0F","label":"fulvus Shaw 1804","value":"fulvus Shaw 1804","lsid":"urn:lsid:zoobank.org:act:BFD7E681-9BC4-46A5-A916-EC19A1288C0F","parentname":"Salmo","namestring":"fulvus","rankgroup":"Species","usageauthors":"Shaw","taxonnamerankid":"70","parentusageuuid":"0B9B48E2-71D4-4858-ABDB-962DDF389A66","cleanprotonym":"Salmo fulvus Shaw, 1804","NomenclaturalCode":"ICZN"},{"tnuuuid":"6B2F4118-DA63-4CF0-A317-262535A69D45","OriginalReferenceUUID":"9F2147ED-91CD-4025-BF99-BE8E95F06464","protonymuuid":"6B2F4118-DA63-4CF0-A317-262535A69D45","label":"phinoc Shaw 1804","value":"phinoc Shaw 1804","lsid":"urn:lsid:zoobank.org:act:6B2F4118-DA63-4CF0-A317-262535A69D45","parentname":"Salmo","namestring":"phinoc","rankgroup":"Species","usageauthors":"Shaw","taxonnamerankid":"70","parentusageuuid":"0B9B48E2-71D4-4858-ABDB-962DDF389A66","cleanprotonym":"Salmo phinoc Shaw, 1804","NomenclaturalCode":"ICZN"},{"tnuuuid":"79C49F1F-D6D0-4132-B4FE-BD78692DA57D","OriginalReferenceUUID":"9F2147ED-91CD-4025-BF99-BE8E95F06464","protonymuuid":"79C49F1F-D6D0-4132-B4FE-BD78692DA57D","label":"rostratus Shaw 1804","value":"rostratus Shaw 1804","lsid":"urn:lsid:zoobank.org:act:79C49F1F-D6D0-4132-B4FE-BD78692DA57D","parentname":"Salmo","namestring":"rostratus","rankgroup":"Species","usageauthors":"Shaw","taxonnamerankid":"70","parentusageuuid":"0B9B48E2-71D4-4858-ABDB-962DDF389A66","cleanprotonym":"Salmo rostratus Shaw, 1804","NomenclaturalCode":"ICZN"},{"tnuuuid":"96822066-30E8-48A8-A86B-4EA92A5FA120","OriginalReferenceUUID":"9F2147ED-91CD-4025-BF99-BE8E95F06464","protonymuuid":"96822066-30E8-48A8-A86B-4EA92A5FA120","label":"reticulata Shaw 1804","value":"reticulata Shaw 1804","lsid":"urn:lsid:zoobank.org:act:96822066-30E8-48A8-A86B-4EA92A5FA120","parentname":"Spatularia","namestring":"reticulata","rankgroup":"Species","usageauthors":"Shaw","taxonnamerankid":"70","parentusageuuid":"2AAC6402-6AF5-493D-B87E-B93691ABF716","cleanprotonym":"Spatularia reticulata Shaw, 1804","NomenclaturalCode":"ICZN"},{"tnuuuid":"32F10638-B57E-4128-B443-8E1AB0A54141","OriginalReferenceUUID":"9F2147ED-91CD-4025-BF99-BE8E95F06464","protonymuuid":"32F10638-B57E-4128-B443-8E1AB0A54141","label":"denticulatus Shaw 1804","value":"denticulatus Shaw 1804","lsid":"urn:lsid:zoobank.org:act:32F10638-B57E-4128-B443-8E1AB0A54141","parentname":"Squalus","namestring":"denticulatus","rankgroup":"Species","usageauthors":"Shaw","taxonnamerankid":"70","parentusageuuid":"2C3AC7A1-1270-4E23-A5F6-0BAC1D351D05","cleanprotonym":"Squalus denticulatus Shaw, 1804","NomenclaturalCode":"ICZN"},{"tnuuuid":"9F83EA2B-39D9-4D60-AC2C-C5C54E00B62A","OriginalReferenceUUID":"9F2147ED-91CD-4025-BF99-BE8E95F06464","protonymuuid":"9F83EA2B-39D9-4D60-AC2C-C5C54E00B62A","label":"gronovianus Shaw 1804","value":"gronovianus Shaw 1804","lsid":"urn:lsid:zoobank.org:act:9F83EA2B-39D9-4D60-AC2C-C5C54E00B62A","parentname":"Squalus","namestring":"gronovianus","rankgroup":"Species","usageauthors":"Shaw","taxonnamerankid":"70","parentusageuuid":"2C3AC7A1-1270-4E23-A5F6-0BAC1D351D05","cleanprotonym":"Squalus gronovianus Shaw, 1804","NomenclaturalCode":"ICZN"},{"tnuuuid":"FD957DE8-2FAF-439F-A12C-81ADEB611726","OriginalReferenceUUID":"9F2147ED-91CD-4025-BF99-BE8E95F06464","protonymuuid":"FD957DE8-2FAF-439F-A12C-81ADEB611726","label":"monensis Shaw 1804","value":"monensis Shaw 1804","lsid":"urn:lsid:zoobank.org:act:FD957DE8-2FAF-439F-A12C-81ADEB611726","parentname":"Squalus","namestring":"monensis","rankgroup":"Species","usageauthors":"Shaw","taxonnamerankid":"70","parentusageuuid":"2C3AC7A1-1270-4E23-A5F6-0BAC1D351D05","cleanprotonym":"Squalus monensis Shaw, 1804","NomenclaturalCode":"ICZN"},{"tnuuuid":"86413326-08A0-4E8E-868E-792B0FA24A6C","OriginalReferenceUUID":"9F2147ED-91CD-4025-BF99-BE8E95F06464","protonymuuid":"86413326-08A0-4E8E-868E-792B0FA24A6C","label":"philippinus Shaw 1804","value":"philippinus Shaw 1804","lsid":"urn:lsid:zoobank.org:act:86413326-08A0-4E8E-868E-792B0FA24A6C","parentname":"Squalus","namestring":"philippinus","rankgroup":"Species","usageauthors":"Shaw","taxonnamerankid":"70","parentusageuuid":"2C3AC7A1-1270-4E23-A5F6-0BAC1D351D05","cleanprotonym":"Squalus philippinus Shaw, 1804","NomenclaturalCode":"ICZN"},{"tnuuuid":"CF188322-71F9-4FC7-B5E6-D077ACADE9BF","OriginalReferenceUUID":"9F2147ED-91CD-4025-BF99-BE8E95F06464","protonymuuid":"CF188322-71F9-4FC7-B5E6-D077ACADE9BF","label":"semisagittatus Shaw 1804","value":"semisagittatus Shaw 1804","lsid":"urn:lsid:zoobank.org:act:CF188322-71F9-4FC7-B5E6-D077ACADE9BF","parentname":"Squalus","namestring":"semisagittatus","rankgroup":"Species","usageauthors":"Shaw","taxonnamerankid":"70","parentusageuuid":"2C3AC7A1-1270-4E23-A5F6-0BAC1D351D05","cleanprotonym":"Squalus semisagittatus Shaw, 1804","NomenclaturalCode":"ICZN"},{"tnuuuid":"2C865A9D-85B6-49E2-9639-657CC51D71FB","OriginalReferenceUUID":"9F2147ED-91CD-4025-BF99-BE8E95F06464","protonymuuid":"2C865A9D-85B6-49E2-9639-657CC51D71FB","label":"tentaculatus Shaw 1804","value":"tentaculatus Shaw 1804","lsid":"urn:lsid:zoobank.org:act:2C865A9D-85B6-49E2-9639-657CC51D71FB","parentname":"Squalus","namestring":"tentaculatus","rankgroup":"Species","usageauthors":"Shaw","taxonnamerankid":"70","parentusageuuid":"2C3AC7A1-1270-4E23-A5F6-0BAC1D351D05","cleanprotonym":"Squalus tentaculatus Shaw, 1804","NomenclaturalCode":"ICZN"},{"tnuuuid":"4F3C7C5F-CB92-45F3-AFE8-3EA93A5E6405","OriginalReferenceUUID":"9F2147ED-91CD-4025-BF99-BE8E95F06464","protonymuuid":"4F3C7C5F-CB92-45F3-AFE8-3EA93A5E6405","label":"zebra Shaw 1804","value":"zebra Shaw 1804","lsid":"urn:lsid:zoobank.org:act:4F3C7C5F-CB92-45F3-AFE8-3EA93A5E6405","parentname":"Squalus","namestring":"zebra","rankgroup":"Species","usageauthors":"Shaw","taxonnamerankid":"70","parentusageuuid":"2C3AC7A1-1270-4E23-A5F6-0BAC1D351D05","cleanprotonym":"Squalus zebra Shaw, 1804","NomenclaturalCode":"ICZN"},{"tnuuuid":"4E3FA932-8145-4961-82EC-B11C27EF6FE9","OriginalReferenceUUID":"9F2147ED-91CD-4025-BF99-BE8E95F06464","protonymuuid":"4E3FA932-8145-4961-82EC-B11C27EF6FE9","label":"foliatus Shaw 1804","value":"foliatus Shaw 1804","lsid":"urn:lsid:zoobank.org:act:4E3FA932-8145-4961-82EC-B11C27EF6FE9","parentname":"Syngnathus","namestring":"foliatus","rankgroup":"Species","usageauthors":"Shaw","taxonnamerankid":"70","parentusageuuid":"33D73D60-0320-4C4E-B7D2-750850C1E302","cleanprotonym":"Syngnathus foliatus Shaw, 1804","NomenclaturalCode":"ICZN"},{"tnuuuid":"CDEB94D9-0F15-468C-83A2-34CCF447C7DD","OriginalReferenceUUID":"9F2147ED-91CD-4025-BF99-BE8E95F06464","protonymuuid":"CDEB94D9-0F15-468C-83A2-34CCF447C7DD","label":"punctatus Shaw 1804","value":"punctatus Shaw 1804","lsid":"urn:lsid:zoobank.org:act:CDEB94D9-0F15-468C-83A2-34CCF447C7DD","parentname":"Tetrodon","namestring":"punctatus","rankgroup":"Species","usageauthors":"Shaw","taxonnamerankid":"70","parentusageuuid":"3F46C42D-0D73-40C3-8423-0CE6C9A4AA29","cleanprotonym":"Tetrodon punctatus Shaw, 1804","NomenclaturalCode":"ICZN"},{"tnuuuid":"D34D11B2-51F1-4ACA-9A02-1B6709DE030C","OriginalReferenceUUID":"9F2147ED-91CD-4025-BF99-BE8E95F06464","protonymuuid":"D34D11B2-51F1-4ACA-9A02-1B6709DE030C","label":"stellatus Shaw 1804","value":"stellatus Shaw 1804","lsid":"urn:lsid:zoobank.org:act:D34D11B2-51F1-4ACA-9A02-1B6709DE030C","parentname":"Tetrodon","namestring":"stellatus","rankgroup":"Species","usageauthors":"Shaw","taxonnamerankid":"70","parentusageuuid":"3F46C42D-0D73-40C3-8423-0CE6C9A4AA29","cleanprotonym":"Tetrodon stellatus Shaw, 1804","NomenclaturalCode":"ICZN"}]}