{"referenceuuid":"300604CC-C620-426B-970B-7D357606B11E","label":"Ashmead, William H.  1900. Classification of the ichneumon flies, or the superfamily Ichneumonoidea. Proceedings of the United States National Museum 23(1206): 1-150.","value":"Ashmead, William H.  1900. Classification of the ichneumon flies, or the superfamily Ichneumonoidea. Proceedings of the United States National Museum 23(1206): 1-150.","authorlist":"Ashmead, William H.","year":"1900","title":"Classification of the ichneumon flies, or the superfamily Ichneumonoidea.","citationdetails":"<em>Proceedings of the United States National Museum<\/em> <b>23<\/b>(1206): 1-150.","volume":"23","number":"1206","edition":"","publisher":"","placepublished":"","pagination":"1-150","startpage":"1","endpage":"150","language":"","languageid":"0","referencetype":"Journal Article","lsid":"","parentreferenceid":"980F75BA-E879-4895-97F6-1268195899B6","parentreference":"Proceedings of the United States National Museum","authors":[[{"familyname":"Ashmead","givenname":"William Harris","gnubuuid":"F671C386-1380-4857-8528-56B2AD6E6FC3"}]],"NomenclaturalActs":[{"tnuuuid":"6581A7AC-2399-4298-B390-65FC57EE1FE6","OriginalReferenceUUID":"300604CC-C620-426B-970B-7D357606B11E","protonymuuid":"6581A7AC-2399-4298-B390-65FC57EE1FE6","label":"Athyreodon Ashmead 1900","value":"Athyreodon Ashmead 1900","lsid":"urn:lsid:zoobank.org:act:6581A7AC-2399-4298-B390-65FC57EE1FE6","parentname":"","namestring":"Athyreodon","rankgroup":"Genus","usageauthors":"Ashmead","taxonnamerankid":"60","parentusageuuid":"","cleanprotonym":"Athyreodon Ashmead, 1900","NomenclaturalCode":"ICZN"},{"tnuuuid":"4E00EB51-4BC5-42D8-9AD3-BAAB2DBEB86B","OriginalReferenceUUID":"","protonymuuid":"3493032F-AE15-4702-B637-CCD311EE239B","label":"Banchogastra  [placeholder record]","value":"Banchogastra  [placeholder record]","lsid":"","parentname":"","namestring":"Banchogastra","rankgroup":"Genus","usageauthors":"Ashmead","taxonnamerankid":"60","parentusageuuid":"","cleanprotonym":"Banchogastra","NomenclaturalCode":"ICZN"},{"tnuuuid":"FCAD3377-35FB-419D-881D-8416B13D3464","OriginalReferenceUUID":"300604CC-C620-426B-970B-7D357606B11E","protonymuuid":"FCAD3377-35FB-419D-881D-8416B13D3464","label":"Glyptocolastes Ashmead 1900","value":"Glyptocolastes Ashmead 1900","lsid":"urn:lsid:zoobank.org:act:FCAD3377-35FB-419D-881D-8416B13D3464","parentname":"","namestring":"Glyptocolastes","rankgroup":"Genus","usageauthors":"Ashmead","taxonnamerankid":"60","parentusageuuid":"","cleanprotonym":"Glyptocolastes Ashmead, 1900","NomenclaturalCode":"ICZN"},{"tnuuuid":"4353B4FB-9125-44C5-BBB4-A65A435E7F33","OriginalReferenceUUID":"300604CC-C620-426B-970B-7D357606B11E","protonymuuid":"FCAD3377-35FB-419D-881D-8416B13D3464","label":"Glyptocolastes Ashmead 1900","value":"Glyptocolastes Ashmead 1900","lsid":"urn:lsid:zoobank.org:act:FCAD3377-35FB-419D-881D-8416B13D3464","parentname":"","namestring":"Glyptocolastes","rankgroup":"Genus","usageauthors":"Ashmead","taxonnamerankid":"60","parentusageuuid":"","cleanprotonym":"Glyptocolastes Ashmead, 1900","NomenclaturalCode":"ICZN"},{"tnuuuid":"448904CF-A271-4C3D-BF15-37D92B51EAE1","OriginalReferenceUUID":"","protonymuuid":"55F13D71-E0BF-4642-9928-62F8C4D59B70","label":"Glyptogastra  [placeholder record]","value":"Glyptogastra  [placeholder record]","lsid":"","parentname":"","namestring":"Glyptogastra","rankgroup":"Genus","usageauthors":"Ashmead","taxonnamerankid":"60","parentusageuuid":"","cleanprotonym":"Glyptogastra","NomenclaturalCode":"ICZN"},{"tnuuuid":"01EC7954-0A21-4F69-AD98-C925D970204D","OriginalReferenceUUID":"","protonymuuid":"74410902-11E7-4857-9CFF-0FC4DB610D38","label":"Pleuroneurophion  [placeholder record]","value":"Pleuroneurophion  [placeholder record]","lsid":"","parentname":"","namestring":"Pleuroneurophion","rankgroup":"Genus","usageauthors":"Ashmead","taxonnamerankid":"60","parentusageuuid":"","cleanprotonym":"Pleuroneurophion","NomenclaturalCode":"ICZN"},{"tnuuuid":"90097F3B-6E16-47FA-9A62-028FA8DC4884","OriginalReferenceUUID":"","protonymuuid":"DD1328B8-B674-4FF9-B7A3-8ECD1C88FFBA","label":"Pycnophion  [placeholder record]","value":"Pycnophion  [placeholder record]","lsid":"urn:lsid:zoobank.org:act:DD1328B8-B674-4FF9-B7A3-8ECD1C88FFBA","parentname":"","namestring":"Pycnophion","rankgroup":"Genus","usageauthors":"Ashmead","taxonnamerankid":"60","parentusageuuid":"","cleanprotonym":"Pycnophion","NomenclaturalCode":"ICZN"},{"tnuuuid":"6B2A7EB0-09F1-4020-A372-DECA654ED823","OriginalReferenceUUID":"300604CC-C620-426B-970B-7D357606B11E","protonymuuid":"6B2A7EB0-09F1-4020-A372-DECA654ED823","label":"nigra Ashmead 1900","value":"nigra Ashmead 1900","lsid":"","parentname":"Banchogastra","namestring":"nigra","rankgroup":"Species","usageauthors":"Ashmead","taxonnamerankid":"70","parentusageuuid":"4E00EB51-4BC5-42D8-9AD3-BAAB2DBEB86B","cleanprotonym":"Banchogastra nigra Ashmead, 1900","NomenclaturalCode":"ICZN"},{"tnuuuid":"E8CA8497-8ABE-48E2-8C33-212B1598CC31","OriginalReferenceUUID":"300604CC-C620-426B-970B-7D357606B11E","protonymuuid":"E8CA8497-8ABE-48E2-8C33-212B1598CC31","label":"texanus Ashmead 1900","value":"texanus Ashmead 1900","lsid":"","parentname":"Glyptocolastes","namestring":"texanus","rankgroup":"Species","usageauthors":"Ashmead","taxonnamerankid":"70","parentusageuuid":"4353B4FB-9125-44C5-BBB4-A65A435E7F33","cleanprotonym":"Glyptocolastes texanus Ashmead, 1900","NomenclaturalCode":"ICZN"},{"tnuuuid":"1A3A5ED0-B358-45E3-A369-1E25FFC10B5C","OriginalReferenceUUID":"300604CC-C620-426B-970B-7D357606B11E","protonymuuid":"1A3A5ED0-B358-45E3-A369-1E25FFC10B5C","label":"hawaiiensis Ashmead 1900","value":"hawaiiensis Ashmead 1900","lsid":"","parentname":"Glyptogastra","namestring":"hawaiiensis","rankgroup":"Species","usageauthors":"Ashmead","taxonnamerankid":"70","parentusageuuid":"448904CF-A271-4C3D-BF15-37D92B51EAE1","cleanprotonym":"Glyptogastra hawaiiensis Ashmead, 1900","NomenclaturalCode":"ICZN"},{"tnuuuid":"5C507F8A-6320-4519-9DFD-63AF382C0D30","OriginalReferenceUUID":"300604CC-C620-426B-970B-7D357606B11E","protonymuuid":"5C507F8A-6320-4519-9DFD-63AF382C0D30","label":"hawaiiensis Ashmead 1900","value":"hawaiiensis Ashmead 1900","lsid":"","parentname":"Pleuroneurophion","namestring":"hawaiiensis","rankgroup":"Species","usageauthors":"Ashmead","taxonnamerankid":"70","parentusageuuid":"01EC7954-0A21-4F69-AD98-C925D970204D","cleanprotonym":"Pleuroneurophion hawaiiensis Ashmead, 1900","NomenclaturalCode":"ICZN"},{"tnuuuid":"65A9DB0B-719F-4533-AD88-D675E1DC2E03","OriginalReferenceUUID":"300604CC-C620-426B-970B-7D357606B11E","protonymuuid":"65A9DB0B-719F-4533-AD88-D675E1DC2E03","label":"molokaiensis Ashmead 1900","value":"molokaiensis Ashmead 1900","lsid":"","parentname":"Pycnophion","namestring":"molokaiensis","rankgroup":"Species","usageauthors":"Ashmead","taxonnamerankid":"70","parentusageuuid":"90097F3B-6E16-47FA-9A62-028FA8DC4884","cleanprotonym":"Pycnophion molokaiensis Ashmead, 1900","NomenclaturalCode":"ICZN"}],"doi":"10.5479\/si.00963801.23-1206.1"}