{"referenceuuid":"DABB183A-F86C-4F48-B6FA-F1CFB1E2E89D","label":"Michel, Bruno & Mervyn W. Mansell.  2018. A new genus and species of owlfly from eastern and southern Africa (Neuroptera: Ascalaphidae). European Journal of Taxonomy(413): 1-12.","value":"Michel, Bruno & Mervyn W. Mansell.  2018. A new genus and species of owlfly from eastern and southern Africa (Neuroptera: Ascalaphidae). European Journal of Taxonomy(413): 1-12.","authorlist":"Michel, Bruno & Mervyn W. Mansell.","year":"2018","title":"A new genus and species of owlfly from eastern and southern Africa (Neuroptera: Ascalaphidae)","citationdetails":"<em>European Journal of Taxonomy<\/em>(413): 1-12.","volume":"","number":"413","edition":"","publisher":"","placepublished":"","pagination":"1-12","startpage":"1","endpage":"12","language":"English","languageid":"19691433","referencetype":"Journal Article","lsid":"urn:lsid:zoobank.org:pub:DABB183A-F86C-4F48-B6FA-F1CFB1E2E89D","parentreferenceid":"DBF45D51-8BA4-45EC-8160-11CE515B6DF4","parentreference":"European journal of taxonomy","authors":[[{"familyname":"Michel","givenname":"Bruno","gnubuuid":"722321B3-407F-490A-9020-ECDB1E835F76"}],[{"familyname":"Mansell","givenname":"Mervyn W.","gnubuuid":"7BD4656A-A2E3-426B-A9B5-DBED06E28284"}]],"NomenclaturalActs":[{"tnuuuid":"6E1F9444-5B07-41AB-9B14-7BC3C6C72E98","OriginalReferenceUUID":"DABB183A-F86C-4F48-B6FA-F1CFB1E2E89D","protonymuuid":"6E1F9444-5B07-41AB-9B14-7BC3C6C72E98","label":"Dorsomitus Michel & Tjeder 2018","value":"Dorsomitus Michel & Tjeder 2018","lsid":"urn:lsid:zoobank.org:act:6E1F9444-5B07-41AB-9B14-7BC3C6C72E98","parentname":"","namestring":"Dorsomitus","rankgroup":"Genus","usageauthors":"Michel & Tjeder","taxonnamerankid":"60","parentusageuuid":"","cleanprotonym":"Dorsomitus Michel & Tjeder in Michel & Mansell, 2018","NomenclaturalCode":"ICZN"},{"tnuuuid":"666BFC9D-4117-426E-880C-B0CAD5E9E600","OriginalReferenceUUID":"DABB183A-F86C-4F48-B6FA-F1CFB1E2E89D","protonymuuid":"666BFC9D-4117-426E-880C-B0CAD5E9E600","label":"tjederi Michel 2018","value":"tjederi Michel 2018","lsid":"urn:lsid:zoobank.org:act:666BFC9D-4117-426E-880C-B0CAD5E9E600","parentname":"Dorsomitus","namestring":"tjederi","rankgroup":"Species","usageauthors":"Michel","taxonnamerankid":"70","parentusageuuid":"6E1F9444-5B07-41AB-9B14-7BC3C6C72E98","cleanprotonym":"Dorsomitus tjederi Michel in Michel & Mansell, 2018","NomenclaturalCode":"ICZN"}],"doi":"10.5852\/ejt.2018.413"}